Workbook

Sheet Summary
A1: AML Platform v1.1 — Test Execution Summary
A2: All figures are formulas over the 'Test Cases' sheet and update as Status is filled in.
A4: Module | B4: Spec Ref | C4: Total | D4: P1 | E4: P2 | F4: P3 | G4: Pass | H4: Fail | I4: Blocked | J4: N/A | K4: Not Run | L4: Executed % | M4: Pass %
A5: Dynamic Customer Fields | B5: §4 | C5: =COUNTIF('Test Cases'!$B$2:$B$319,$A5) | D5: =COUNTIFS('Test Cases'!$B$2:$B$319,$A5,'Test Cases'!$I$2:$I$319,"P1") | E5: =COUNTIFS('Test Cases'!$B$2:$B$319,$A5,'Test Cases'!$I$2:$I$319,"P2") | F5: =COUNTIFS('Test Cases'!$B$2:$B$319,$A5,'Test Cases'!$I$2:$I$319,"P3") | G5: =COUNTIFS('Test Cases'!$B$2:$B$319,$A5,'Test Cases'!$L$2:$L$319,"Pass") | H5: =COUNTIFS('Test Cases'!$B$2:$B$319,$A5,'Test Cases'!$L$2:$L$319,"Fail") | I5: =COUNTIFS('Test Cases'!$B$2:$B$319,$A5,'Test Cases'!$L$2:$L$319,"Blocked") | J5: =COUNTIFS('Test Cases'!$B$2:$B$319,$A5,'Test Cases'!$L$2:$L$319,"N/A") | K5: =COUNTIFS('Test Cases'!$B$2:$B$319,$A5,'Test Cases'!$L$2:$L$319,"Not Run") | L5: =IF(C5=0,0,(C5-K5)/C5) | M5: =IF((C5-K5-J5)=0,0,G5/(C5-K5-J5))
A6: Customer Profile & Search | B6: §6–7 | C6: =COUNTIF('Test Cases'!$B$2:$B$319,$A6) | D6: =COUNTIFS('Test Cases'!$B$2:$B$319,$A6,'Test Cases'!$I$2:$I$319,"P1") | E6: =COUNTIFS('Test Cases'!$B$2:$B$319,$A6,'Test Cases'!$I$2:$I$319,"P2") | F6: =COUNTIFS('Test Cases'!$B$2:$B$319,$A6,'Test Cases'!$I$2:$I$319,"P3") | G6: =COUNTIFS('Test Cases'!$B$2:$B$319,$A6,'Test Cases'!$L$2:$L$319,"Pass") | H6: =COUNTIFS('Test Cases'!$B$2:$B$319,$A6,'Test Cases'!$L$2:$L$319,"Fail") | I6: =COUNTIFS('Test Cases'!$B$2:$B$319,$A6,'Test Cases'!$L$2:$L$319,"Blocked") | J6: =COUNTIFS('Test Cases'!$B$2:$B$319,$A6,'Test Cases'!$L$2:$L$319,"N/A") | K6: =COUNTIFS('Test Cases'!$B$2:$B$319,$A6,'Test Cases'!$L$2:$L$319,"Not Run") | L6: =IF(C6=0,0,(C6-K6)/C6) | M6: =IF((C6-K6-J6)=0,0,G6/(C6-K6-J6))
A7: Customer Acceptance, CDD & Beneficial Ownership | B7: §18 | C7: =COUNTIF('Test Cases'!$B$2:$B$319,$A7) | D7: =COUNTIFS('Test Cases'!$B$2:$B$319,$A7,'Test Cases'!$I$2:$I$319,"P1") | E7: =COUNTIFS('Test Cases'!$B$2:$B$319,$A7,'Test Cases'!$I$2:$I$319,"P2") | F7: =COUNTIFS('Test Cases'!$B$2:$B$319,$A7,'Test Cases'!$I$2:$I$319,"P3") | G7: =COUNTIFS('Test Cases'!$B$2:$B$319,$A7,'Test Cases'!$L$2:$L$319,"Pass") | H7: =COUNTIFS('Test Cases'!$B$2:$B$319,$A7,'Test Cases'!$L$2:$L$319,"Fail") | I7: =COUNTIFS('Test Cases'!$B$2:$B$319,$A7,'Test Cases'!$L$2:$L$319,"Blocked") | J7: =COUNTIFS('Test Cases'!$B$2:$B$319,$A7,'Test Cases'!$L$2:$L$319,"N/A") | K7: =COUNTIFS('Test Cases'!$B$2:$B$319,$A7,'Test Cases'!$L$2:$L$319,"Not Run") | L7: =IF(C7=0,0,(C7-K7)/C7) | M7: =IF((C7-K7-J7)=0,0,G7/(C7-K7-J7))
A8: Risk Methodology Configuration | B8: §5 | C8: =COUNTIF('Test Cases'!$B$2:$B$319,$A8) | D8: =COUNTIFS('Test Cases'!$B$2:$B$319,$A8,'Test Cases'!$I$2:$I$319,"P1") | E8: =COUNTIFS('Test Cases'!$B$2:$B$319,$A8,'Test Cases'!$I$2:$I$319,"P2") | F8: =COUNTIFS('Test Cases'!$B$2:$B$319,$A8,'Test Cases'!$I$2:$I$319,"P3") | G8: =COUNTIFS('Test Cases'!$B$2:$B$319,$A8,'Test Cases'!$L$2:$L$319,"Pass") | H8: =COUNTIFS('Test Cases'!$B$2:$B$319,$A8,'Test Cases'!$L$2:$L$319,"Fail") | I8: =COUNTIFS('Test Cases'!$B$2:$B$319,$A8,'Test Cases'!$L$2:$L$319,"Blocked") | J8: =COUNTIFS('Test Cases'!$B$2:$B$319,$A8,'Test Cases'!$L$2:$L$319,"N/A") | K8: =COUNTIFS('Test Cases'!$B$2:$B$319,$A8,'Test Cases'!$L$2:$L$319,"Not Run") | L8: =IF(C8=0,0,(C8-K8)/C8) | M8: =IF((C8-K8-J8)=0,0,G8/(C8-K8-J8))
A9: Risk Engine Calculation | B9: §5, §27 | C9: =COUNTIF('Test Cases'!$B$2:$B$319,$A9) | D9: =COUNTIFS('Test Cases'!$B$2:$B$319,$A9,'Test Cases'!$I$2:$I$319,"P1") | E9: =COUNTIFS('Test Cases'!$B$2:$B$319,$A9,'Test Cases'!$I$2:$I$319,"P2") | F9: =COUNTIFS('Test Cases'!$B$2:$B$319,$A9,'Test Cases'!$I$2:$I$319,"P3") | G9: =COUNTIFS('Test Cases'!$B$2:$B$319,$A9,'Test Cases'!$L$2:$L$319,"Pass") | H9: =COUNTIFS('Test Cases'!$B$2:$B$319,$A9,'Test Cases'!$L$2:$L$319,"Fail") | I9: =COUNTIFS('Test Cases'!$B$2:$B$319,$A9,'Test Cases'!$L$2:$L$319,"Blocked") | J9: =COUNTIFS('Test Cases'!$B$2:$B$319,$A9,'Test Cases'!$L$2:$L$319,"N/A") | K9: =COUNTIFS('Test Cases'!$B$2:$B$319,$A9,'Test Cases'!$L$2:$L$319,"Not Run") | L9: =IF(C9=0,0,(C9-K9)/C9) | M9: =IF((C9-K9-J9)=0,0,G9/(C9-K9-J9))
A10: Risk Override & Review | B10: §5 | C10: =COUNTIF('Test Cases'!$B$2:$B$319,$A10) | D10: =COUNTIFS('Test Cases'!$B$2:$B$319,$A10,'Test Cases'!$I$2:$I$319,"P1") | E10: =COUNTIFS('Test Cases'!$B$2:$B$319,$A10,'Test Cases'!$I$2:$I$319,"P2") | F10: =COUNTIFS('Test Cases'!$B$2:$B$319,$A10,'Test Cases'!$I$2:$I$319,"P3") | G10: =COUNTIFS('Test Cases'!$B$2:$B$319,$A10,'Test Cases'!$L$2:$L$319,"Pass") | H10: =COUNTIFS('Test Cases'!$B$2:$B$319,$A10,'Test Cases'!$L$2:$L$319,"Fail") | I10: =COUNTIFS('Test Cases'!$B$2:$B$319,$A10,'Test Cases'!$L$2:$L$319,"Blocked") | J10: =COUNTIFS('Test Cases'!$B$2:$B$319,$A10,'Test Cases'!$L$2:$L$319,"N/A") | K10: =COUNTIFS('Test Cases'!$B$2:$B$319,$A10,'Test Cases'!$L$2:$L$319,"Not Run") | L10: =IF(C10=0,0,(C10-K10)/C10) | M10: =IF((C10-K10-J10)=0,0,G10/(C10-K10-J10))
A11: Wallets & Party Resolution | B11: §7 | C11: =COUNTIF('Test Cases'!$B$2:$B$319,$A11) | D11: =COUNTIFS('Test Cases'!$B$2:$B$319,$A11,'Test Cases'!$I$2:$I$319,"P1") | E11: =COUNTIFS('Test Cases'!$B$2:$B$319,$A11,'Test Cases'!$I$2:$I$319,"P2") | F11: =COUNTIFS('Test Cases'!$B$2:$B$319,$A11,'Test Cases'!$I$2:$I$319,"P3") | G11: =COUNTIFS('Test Cases'!$B$2:$B$319,$A11,'Test Cases'!$L$2:$L$319,"Pass") | H11: =COUNTIFS('Test Cases'!$B$2:$B$319,$A11,'Test Cases'!$L$2:$L$319,"Fail") | I11: =COUNTIFS('Test Cases'!$B$2:$B$319,$A11,'Test Cases'!$L$2:$L$319,"Blocked") | J11: =COUNTIFS('Test Cases'!$B$2:$B$319,$A11,'Test Cases'!$L$2:$L$319,"N/A") | K11: =COUNTIFS('Test Cases'!$B$2:$B$319,$A11,'Test Cases'!$L$2:$L$319,"Not Run") | L11: =IF(C11=0,0,(C11-K11)/C11) | M11: =IF((C11-K11-J11)=0,0,G11/(C11-K11-J11))
A12: Transaction Ingestion & Idempotency | B12: §16 | C12: =COUNTIF('Test Cases'!$B$2:$B$319,$A12) | D12: =COUNTIFS('Test Cases'!$B$2:$B$319,$A12,'Test Cases'!$I$2:$I$319,"P1") | E12: =COUNTIFS('Test Cases'!$B$2:$B$319,$A12,'Test Cases'!$I$2:$I$319,"P2") | F12: =COUNTIFS('Test Cases'!$B$2:$B$319,$A12,'Test Cases'!$I$2:$I$319,"P3") | G12: =COUNTIFS('Test Cases'!$B$2:$B$319,$A12,'Test Cases'!$L$2:$L$319,"Pass") | H12: =COUNTIFS('Test Cases'!$B$2:$B$319,$A12,'Test Cases'!$L$2:$L$319,"Fail") | I12: =COUNTIFS('Test Cases'!$B$2:$B$319,$A12,'Test Cases'!$L$2:$L$319,"Blocked") | J12: =COUNTIFS('Test Cases'!$B$2:$B$319,$A12,'Test Cases'!$L$2:$L$319,"N/A") | K12: =COUNTIFS('Test Cases'!$B$2:$B$319,$A12,'Test Cases'!$L$2:$L$319,"Not Run") | L12: =IF(C12=0,0,(C12-K12)/C12) | M12: =IF((C12-K12-J12)=0,0,G12/(C12-K12-J12))
A13: Currency, Time Zone & Calendar | B13: §24 | C13: =COUNTIF('Test Cases'!$B$2:$B$319,$A13) | D13: =COUNTIFS('Test Cases'!$B$2:$B$319,$A13,'Test Cases'!$I$2:$I$319,"P1") | E13: =COUNTIFS('Test Cases'!$B$2:$B$319,$A13,'Test Cases'!$I$2:$I$319,"P2") | F13: =COUNTIFS('Test Cases'!$B$2:$B$319,$A13,'Test Cases'!$I$2:$I$319,"P3") | G13: =COUNTIFS('Test Cases'!$B$2:$B$319,$A13,'Test Cases'!$L$2:$L$319,"Pass") | H13: =COUNTIFS('Test Cases'!$B$2:$B$319,$A13,'Test Cases'!$L$2:$L$319,"Fail") | I13: =COUNTIFS('Test Cases'!$B$2:$B$319,$A13,'Test Cases'!$L$2:$L$319,"Blocked") | J13: =COUNTIFS('Test Cases'!$B$2:$B$319,$A13,'Test Cases'!$L$2:$L$319,"N/A") | K13: =COUNTIFS('Test Cases'!$B$2:$B$319,$A13,'Test Cases'!$L$2:$L$319,"Not Run") | L13: =IF(C13=0,0,(C13-K13)/C13) | M13: =IF((C13-K13-J13)=0,0,G13/(C13-K13-J13))
A14: Rule Builder & Execution | B14: §8 | C14: =COUNTIF('Test Cases'!$B$2:$B$319,$A14) | D14: =COUNTIFS('Test Cases'!$B$2:$B$319,$A14,'Test Cases'!$I$2:$I$319,"P1") | E14: =COUNTIFS('Test Cases'!$B$2:$B$319,$A14,'Test Cases'!$I$2:$I$319,"P2") | F14: =COUNTIFS('Test Cases'!$B$2:$B$319,$A14,'Test Cases'!$I$2:$I$319,"P3") | G14: =COUNTIFS('Test Cases'!$B$2:$B$319,$A14,'Test Cases'!$L$2:$L$319,"Pass") | H14: =COUNTIFS('Test Cases'!$B$2:$B$319,$A14,'Test Cases'!$L$2:$L$319,"Fail") | I14: =COUNTIFS('Test Cases'!$B$2:$B$319,$A14,'Test Cases'!$L$2:$L$319,"Blocked") | J14: =COUNTIFS('Test Cases'!$B$2:$B$319,$A14,'Test Cases'!$L$2:$L$319,"N/A") | K14: =COUNTIFS('Test Cases'!$B$2:$B$319,$A14,'Test Cases'!$L$2:$L$319,"Not Run") | L14: =IF(C14=0,0,(C14-K14)/C14) | M14: =IF((C14-K14-J14)=0,0,G14/(C14-K14-J14))
A15: Alert Deduplication & Lifecycle | B15: §10 | C15: =COUNTIF('Test Cases'!$B$2:$B$319,$A15) | D15: =COUNTIFS('Test Cases'!$B$2:$B$319,$A15,'Test Cases'!$I$2:$I$319,"P1") | E15: =COUNTIFS('Test Cases'!$B$2:$B$319,$A15,'Test Cases'!$I$2:$I$319,"P2") | F15: =COUNTIFS('Test Cases'!$B$2:$B$319,$A15,'Test Cases'!$I$2:$I$319,"P3") | G15: =COUNTIFS('Test Cases'!$B$2:$B$319,$A15,'Test Cases'!$L$2:$L$319,"Pass") | H15: =COUNTIFS('Test Cases'!$B$2:$B$319,$A15,'Test Cases'!$L$2:$L$319,"Fail") | I15: =COUNTIFS('Test Cases'!$B$2:$B$319,$A15,'Test Cases'!$L$2:$L$319,"Blocked") | J15: =COUNTIFS('Test Cases'!$B$2:$B$319,$A15,'Test Cases'!$L$2:$L$319,"N/A") | K15: =COUNTIFS('Test Cases'!$B$2:$B$319,$A15,'Test Cases'!$L$2:$L$319,"Not Run") | L15: =IF(C15=0,0,(C15-K15)/C15) | M15: =IF((C15-K15-J15)=0,0,G15/(C15-K15-J15))
A16: Case Management | B16: §10 | C16: =COUNTIF('Test Cases'!$B$2:$B$319,$A16) | D16: =COUNTIFS('Test Cases'!$B$2:$B$319,$A16,'Test Cases'!$I$2:$I$319,"P1") | E16: =COUNTIFS('Test Cases'!$B$2:$B$319,$A16,'Test Cases'!$I$2:$I$319,"P2") | F16: =COUNTIFS('Test Cases'!$B$2:$B$319,$A16,'Test Cases'!$I$2:$I$319,"P3") | G16: =COUNTIFS('Test Cases'!$B$2:$B$319,$A16,'Test Cases'!$L$2:$L$319,"Pass") | H16: =COUNTIFS('Test Cases'!$B$2:$B$319,$A16,'Test Cases'!$L$2:$L$319,"Fail") | I16: =COUNTIFS('Test Cases'!$B$2:$B$319,$A16,'Test Cases'!$L$2:$L$319,"Blocked") | J16: =COUNTIFS('Test Cases'!$B$2:$B$319,$A16,'Test Cases'!$L$2:$L$319,"N/A") | K16: =COUNTIFS('Test Cases'!$B$2:$B$319,$A16,'Test Cases'!$L$2:$L$319,"Not Run") | L16: =IF(C16=0,0,(C16-K16)/C16) | M16: =IF((C16-K16-J16)=0,0,G16/(C16-K16-J16))
... A35: Jurisdiction Configuration & Seed Data | B35: §34, §36 | C35: =COUNTIF('Test Cases'!$B$2:$B$319,$A35) | D35: =COUNTIFS('Test Cases'!$B$2:$B$319,$A35,'Test Cases'!$I$2:$I$319,"P1") | E35: =COUNTIFS('Test Cases'!$B$2:$B$319,$A35,'Test Cases'!$I$2:$I$319,"P2") | F35: =COUNTIFS('Test Cases'!$B$2:$B$319,$A35,'Test Cases'!$I$2:$I$319,"P3") | G35: =COUNTIFS('Test Cases'!$B$2:$B$319,$A35,'Test Cases'!$L$2:$L$319,"Pass") | H35: =COUNTIFS('Test Cases'!$B$2:$B$319,$A35,'Test Cases'!$L$2:$L$319,"Fail") | I35: =COUNTIFS('Test Cases'!$B$2:$B$319,$A35,'Test Cases'!$L$2:$L$319,"Blocked") | J35: =COUNTIFS('Test Cases'!$B$2:$B$319,$A35,'Test Cases'!$L$2:$L$319,"N/A") | K35: =COUNTIFS('Test Cases'!$B$2:$B$319,$A35,'Test Cases'!$L$2:$L$319,"Not Run") | L35: =IF(C35=0,0,(C35-K35)/C35) | M35: =IF((C35-K35-J35)=0,0,G35/(C35-K35-J35))
A36: Total | C36: =SUM(C5:C35) | D36: =SUM(D5:D35) | E36: =SUM(E5:E35) | F36: =SUM(F5:F35) | G36: =SUM(G5:G35) | H36: =SUM(H5:H35) | I36: =SUM(I5:I35) | J36: =SUM(J5:J35) | K36: =SUM(K5:K35) | L36: =IF(C36=0,0,(C36-K36)/C36) | M36: =IF((C36-K36-J36)=0,0,G36/(C36-K36-J36))

Sheet Test Cases
A1: TC ID | B1: Module | C1: Spec Ref | D1: Title | E1: Preconditions | F1: Test Steps | G1: Test Data | H1: Expected Result | I1: Priority | J1: Test Type | K1: Test Level | L1: Status | M1: Actual Result | N1: Tester | O1: Execution Date | P1: Defect ID | Q1: Notes
A2: TC-FLD-001 | B2: Dynamic Customer Fields | C2: §4 | D2: Create a new short-text field as draft | E2: Admin with field-config permission | F2: 1. Open Customer Field Configuration 2. Click New field 3. Enter code, label, type=Short text, group=Core Details 4. Save as draft | G2: code=MOTHER_NAME | H2: Field saved with status Draft, version 1; not visible on customer forms | I2: P1 | J2: Functional | K2: E2E | L2: Pass | M2: Field MOTHER_NAME_21260D saved as Draft v1 (not in form metadata); after publish status Published and returned by GET /api/config/customer-fields for Individual — no deployment. | N2: Claude (automated test suite) | O2: 46310 | Q2: Automated: FieldsTests.Create_draft_and_publish_without_deployment
A3: TC-FLD-002 | B3: Dynamic Customer Fields | C3: §4 | D3: Publish a draft field without code deployment | E3: Draft field exists | F3: 1. Open draft field 2. Click Publish 3. Approve if four-eyes is configured 4. Open an individual customer form | G3: MOTHER_NAME | H3: Field status Published; field renders on the individual form from API metadata with no frontend change | I3: P1 | J3: Functional | K3: E2E | L3: Pass | M3: Field MOTHER_NAME_21260D saved as Draft v1 (not in form metadata); after publish status Published and returned by GET /api/config/customer-fields for Individual — no deployment. | N3: Claude (automated test suite) | O3: 46310 | Q3: Automated: FieldsTests.Create_draft_and_publish_without_deployment
A4: TC-FLD-003 | B4: Dynamic Customer Fields | C4: §4 | D4: Add 'Expected Monthly Cash Deposits' as required decimal for individuals | E4: Admin logged in | F4: 1. Create field type=Decimal, required for Individual, group=Financial Profile, searchable=true, min=0 2. Publish 3. Create an individual customer without the field | G4: EXP_MONTHLY_CASH | H4: Save rejected with validation error naming the field; corporate customer form does not require it | I4: P1 | J4: Functional | K4: E2E | L4: Pass | M4: POST /api/customers without EXP_CASH_123C7F → 400: EXP_CASH_123C7F label (EXP_CASH_123C7F) is required for Individual customers. | N4: Claude (automated test suite) | O4: 46310 | Q4: Automated: FieldsTests.Required_decimal_enforced
A5: TC-FLD-004 | B5: Dynamic Customer Fields | C5: §4 | D5: Field applicability by customer type | E5: Field applicable to Corporate only | F5: 1. Open Individual form 2. Open Corporate form | G5: INCORP_REG_NO | H5: Field hidden on Individual, shown on Corporate | I5: P2 | J5: Functional | K5: E2E | L5: Pass | M5: INCORP_REG_NO absent from Individual metadata, present for Corporate; API rejects it for an Individual (400). | N5: Claude (automated test suite) | O5: 46310 | Q5: Automated: FieldsTests.Applicability_by_type
A6: TC-FLD-005 | B6: Dynamic Customer Fields | C6: §4 | D6: Server-side validation of decimal type | E6: Decimal field published | F6: 1. Call PUT /api/customers/{id}/attributes with a text value bypassing UI | G6: value="abc" | H6: HTTP 400 problem-details with field code and message; value not persisted | I6: P1 | J6: Negative | K6: API | L6: Pass | M6: 400 problem-details: DEC_46462F label (DEC_46462F): value must be a decimal number.; 0 values stored. | N6: Claude (automated test suite) | O6: 46310 | Q6: Automated: FieldsTests.Decimal_rejects_text
A7: TC-FLD-006 | B7: Dynamic Customer Fields | C7: §4 | D7: Server-side validation of regex rule | E7: Identifier field with regex ^[0-9]{10}$ | F7: 1. Submit value with 9 digits via API | G7: 123456789 | H7: HTTP 400; no value stored | I7: P2 | J7: Negative | K7: API | L7: Pass | M7: SECONDARY_ID with 9 digits rejected (400) against ^[0-9]{10}$; no value stored. | N7: Claude (automated test suite) | O7: 46310 | Q7: Automated: FieldsTests.Regex_validated
A8: TC-FLD-007 | B8: Dynamic Customer Fields | C8: §4 | D8: Single-select accepts only active options | E8: Field with options A,B; option B inactive | F8: 1. Submit value B via API | G8: B | H8: Rejected as invalid option | I8: P2 | J8: Negative | K8: API | L8: Pass | M8: Inactive option B rejected (400); active option A accepted. | N8: Claude (automated test suite) | O8: 46310 | Q8: Automated: FieldsTests.Single_select_active_options_only
A9: TC-FLD-008 | B9: Dynamic Customer Fields | C9: §4 | D9: Multi-select stores multiple values | E9: Multi-select field published | F9: 1. Select 3 options 2. Save 3. Reload profile | G9: A,C,D | H9: All 3 values persisted and displayed in sort order | I9: P3 | J9: Functional | K9: E2E | L9: Pass | M9: Submitted [D,A,C]; reloaded display 'A,C,D' (option sort order). | N9: Claude (automated test suite) | O9: 46310 | Q9: Automated: FieldsTests.Multi_select_persisted_sorted
A10: TC-FLD-009 | B10: Dynamic Customer Fields | C10: §4 | D10: Effective-dated field values | E10: Field with effective dates | F10: 1. Set value V1 effective 2026-01-01 2. Set V2 effective 2026-06-01 3. Query value as of 2026-03-01 and today | G10: V1,V2 | H10: As-of query returns V1; current returns V2 | I10: P2 | J10: Functional | K10: Integration | L10: Pass | M10: As of 2026-03-01 → 'ar' (V1); current → 'en' (V2). | N10: Claude (automated test suite) | O10: 46310 | Q10: Automated: FieldsTests.Effective_dated_values
A11: TC-FLD-010 | B11: Dynamic Customer Fields | C11: §4 | D11: Field change history recorded | E11: Customer with value | F11: 1. Change value with reason | G11: old=5000,new=9000 | H11: History row with old, new, actor, UTC timestamp, reason | I11: P1 | J11: Functional | K11: Integration | L11: Pass | M11: History row: old=5000 new=9000 actor=manager at 2026-10-14T23:59:42.558033Z (UTC) reason='customer update'. | N11: Claude (automated test suite) | O11: 46310 | Q11: Automated: FieldsTests.Change_history
A12: TC-FLD-011 | B12: Dynamic Customer Fields | C12: §4 | D12: Incompatible type change blocked | E12: Field with stored decimal values | F12: 1. Edit field type to Boolean 2. Publish | G12: type change | H12: Publish blocked with message listing affected values; existing values unchanged | I12: P1 | J12: Negative | K12: Integration | L12: Pass | M12: Publish blocked (409): Publish blocked: Type change Decimal -> Boolean is incompatible with 1 stored value(s) (customers: 49).; stored value 12.5 unchanged. | N12: Claude (automated test suite) | O12: 46310 | Q12: Automated: FieldsTests.Incompatible_type_change_blocked
A13: TC-FLD-012 | B13: Dynamic Customer Fields | C13: §4 | D13: Deactivate field preserves history | E13: Field with values | F13: 1. Deactivate field 2. Open customer audit/history | G13: — | H13: Field hidden on forms; historical values still visible in history | I13: P2 | J13: Functional | K13: E2E | L13: Pass | M13: After deactivation the field is absent from form metadata; history still returns the stored value 'hello'. | N13: Claude (automated test suite) | O13: 46310 | Q13: Automated: FieldsTests.Deactivate_preserves_history
... A319: TC-JUR-005 | B319: Jurisdiction Configuration & Seed Data | C319: §34, §36 | D319: No real data in seed | E319: — | F319: 1. Review seed scripts | G319: — | H319: Only fictitious data | I319: P1 | J319: Data | K319: Unit | L319: Pass | M319: Seed reviewed: list sources suffixed -TEST and flagged test data, customers/entries use synthetic 'Test…/Fakename' names, FX rates labelled 'SAMPLE TEST DATA - not a market rate'; no real persons, accounts or secrets. | N319: Claude (automated test suite) | O319: 46310 | Q319: Automated: RetentionJurisdictionTests.Seed_has_only_fictitious_data

Sheet Legend
A1: How to use | B1: Fill the shaded columns on 'Test Cases' (Status, Actual Result, Tester, Execution Date, Defect ID, Notes). Status is a dropdown; the Summary sheet updates automatically.
A2: Example row | B2: TC-FLD-001 → Status: Pass · Actual Result: Field saved as Draft v1, hidden on forms · Tester: QA1 · Execution Date: 2026-10-20 · Defect ID: (blank)
A3: TC ID | B3: TC-<module code>-<sequence>. Module codes: FLD=Dynamic Customer Fields, CUS=Customer Profile & Search, CDD=Customer Acceptance, CDD & Beneficial Ownership, RCF=Risk Methodology Configuration, RSK=Risk Engine Calculation, OVR=Risk Override & Review, WAL=Wallets & Party Resolution, ING=Transaction Ingestion & Idempotency, FXT=Currency, Time Zone & Calendar, RUL=Rule Builder & Execution, ALR=Alert Deduplication & Lifecycle, CAS=Case Management, SCR=Screening & List Management, ACT=Compliance Actions & Freezing, RTD=Real-time Decisioning, R16=Payment Transparency (R.16), STR=Regulatory Reporting (STR/SAR), TOF=Tipping-off Controls, ENT=Entity Resolution & Device Intelligence, AGT=Agent & Merchant Risk, CFG=Configuration Integrity, EFF=Monitoring Effectiveness & Tuning, QA=Investigation QA, RET=Retention & Legal Hold, SEC=Security & Audit, API=API Contracts, RPT=Reports & Exports, L10N=Localization & Arabic Name Matching, NFR=Non-functional (Performance, Availability, DR), UI=User Interface States, JUR=Jurisdiction Configuration & Seed Data
A4: Spec Ref | B4: Section of AML Platform AI Implementation Specification v1.1.
A5: Priority | B5: P1 = regulatory, security or data-integrity critical (must pass before go-live). P2 = important functional. P3 = usability / nice to have.
A6: Test Type | B6: Functional, Negative, Security, Performance, Integration, Data, UI.
A7: Test Level | B7: Unit = domain/application service tests; Integration = with DB/queues/adapters; API = HTTP contract tests; E2E = through the UI; UAT = business/operations acceptance (e.g. DR).
A8: Status | B8: Not Run, Pass, Fail, Blocked, N/A. Pass % excludes Not Run and N/A.
A9: Jurisdiction values | B9: Thresholds, deadlines and retention periods in these tests are placeholders. Use the values confirmed by compliance in spec section 34.
A10: Test data | B10: Use only fictitious data. Never use real customer or sanctions-list data outside controlled test lists.
