Workbook

Sheet Summary
A1: Transaction Monitoring Scenarios — Test Summary
A2: Figures are formulas over 'Test Cases' and update as Status is filled in. Thresholds are configurable defaults, not regulatory values.
A4: Category | B4: Scenarios | C4: Test Cases | D4: Positive | E4: Negative | F4: Boundary | G4: Edge | H4: Pass | I4: Fail | J4: Blocked | K4: Not Run | L4: Executed % | M4: Pass %
A5: Velocity & Frequency | B5: =COUNTIF('Scenario Catalogue'!$B$2:$B$121,A5) | C5: =COUNTIF('Test Cases'!$B$2:$B$315,A5) | D5: =COUNTIFS('Test Cases'!$B$2:$B$315,$A5,'Test Cases'!$E$2:$E$315,"Positive") | E5: =COUNTIFS('Test Cases'!$B$2:$B$315,$A5,'Test Cases'!$E$2:$E$315,"Negative") | F5: =COUNTIFS('Test Cases'!$B$2:$B$315,$A5,'Test Cases'!$E$2:$E$315,"Boundary") | G5: =COUNTIFS('Test Cases'!$B$2:$B$315,$A5,'Test Cases'!$E$2:$E$315,"Edge") | H5: =COUNTIFS('Test Cases'!$B$2:$B$315,$A5,'Test Cases'!$J$2:$J$315,"Pass") | I5: =COUNTIFS('Test Cases'!$B$2:$B$315,$A5,'Test Cases'!$J$2:$J$315,"Fail") | J5: =COUNTIFS('Test Cases'!$B$2:$B$315,$A5,'Test Cases'!$J$2:$J$315,"Blocked") | K5: =COUNTIFS('Test Cases'!$B$2:$B$315,$A5,'Test Cases'!$J$2:$J$315,"Not Run") | L5: =IF(C5=0,0,(C5-K5)/C5) | M5: =IF((H5+I5+J5)=0,0,H5/(H5+I5+J5))
A6: Amount & Thresholds | B6: =COUNTIF('Scenario Catalogue'!$B$2:$B$121,A6) | C6: =COUNTIF('Test Cases'!$B$2:$B$315,A6) | D6: =COUNTIFS('Test Cases'!$B$2:$B$315,$A6,'Test Cases'!$E$2:$E$315,"Positive") | E6: =COUNTIFS('Test Cases'!$B$2:$B$315,$A6,'Test Cases'!$E$2:$E$315,"Negative") | F6: =COUNTIFS('Test Cases'!$B$2:$B$315,$A6,'Test Cases'!$E$2:$E$315,"Boundary") | G6: =COUNTIFS('Test Cases'!$B$2:$B$315,$A6,'Test Cases'!$E$2:$E$315,"Edge") | H6: =COUNTIFS('Test Cases'!$B$2:$B$315,$A6,'Test Cases'!$J$2:$J$315,"Pass") | I6: =COUNTIFS('Test Cases'!$B$2:$B$315,$A6,'Test Cases'!$J$2:$J$315,"Fail") | J6: =COUNTIFS('Test Cases'!$B$2:$B$315,$A6,'Test Cases'!$J$2:$J$315,"Blocked") | K6: =COUNTIFS('Test Cases'!$B$2:$B$315,$A6,'Test Cases'!$J$2:$J$315,"Not Run") | L6: =IF(C6=0,0,(C6-K6)/C6) | M6: =IF((H6+I6+J6)=0,0,H6/(H6+I6+J6))
A7: Structuring & Smurfing | B7: =COUNTIF('Scenario Catalogue'!$B$2:$B$121,A7) | C7: =COUNTIF('Test Cases'!$B$2:$B$315,A7) | D7: =COUNTIFS('Test Cases'!$B$2:$B$315,$A7,'Test Cases'!$E$2:$E$315,"Positive") | E7: =COUNTIFS('Test Cases'!$B$2:$B$315,$A7,'Test Cases'!$E$2:$E$315,"Negative") | F7: =COUNTIFS('Test Cases'!$B$2:$B$315,$A7,'Test Cases'!$E$2:$E$315,"Boundary") | G7: =COUNTIFS('Test Cases'!$B$2:$B$315,$A7,'Test Cases'!$E$2:$E$315,"Edge") | H7: =COUNTIFS('Test Cases'!$B$2:$B$315,$A7,'Test Cases'!$J$2:$J$315,"Pass") | I7: =COUNTIFS('Test Cases'!$B$2:$B$315,$A7,'Test Cases'!$J$2:$J$315,"Fail") | J7: =COUNTIFS('Test Cases'!$B$2:$B$315,$A7,'Test Cases'!$J$2:$J$315,"Blocked") | K7: =COUNTIFS('Test Cases'!$B$2:$B$315,$A7,'Test Cases'!$J$2:$J$315,"Not Run") | L7: =IF(C7=0,0,(C7-K7)/C7) | M7: =IF((H7+I7+J7)=0,0,H7/(H7+I7+J7))
A8: Rapid Movement & Pass-through | B8: =COUNTIF('Scenario Catalogue'!$B$2:$B$121,A8) | C8: =COUNTIF('Test Cases'!$B$2:$B$315,A8) | D8: =COUNTIFS('Test Cases'!$B$2:$B$315,$A8,'Test Cases'!$E$2:$E$315,"Positive") | E8: =COUNTIFS('Test Cases'!$B$2:$B$315,$A8,'Test Cases'!$E$2:$E$315,"Negative") | F8: =COUNTIFS('Test Cases'!$B$2:$B$315,$A8,'Test Cases'!$E$2:$E$315,"Boundary") | G8: =COUNTIFS('Test Cases'!$B$2:$B$315,$A8,'Test Cases'!$E$2:$E$315,"Edge") | H8: =COUNTIFS('Test Cases'!$B$2:$B$315,$A8,'Test Cases'!$J$2:$J$315,"Pass") | I8: =COUNTIFS('Test Cases'!$B$2:$B$315,$A8,'Test Cases'!$J$2:$J$315,"Fail") | J8: =COUNTIFS('Test Cases'!$B$2:$B$315,$A8,'Test Cases'!$J$2:$J$315,"Blocked") | K8: =COUNTIFS('Test Cases'!$B$2:$B$315,$A8,'Test Cases'!$J$2:$J$315,"Not Run") | L8: =IF(C8=0,0,(C8-K8)/C8) | M8: =IF((H8+I8+J8)=0,0,H8/(H8+I8+J8))
A9: Fan-in / Fan-out | B9: =COUNTIF('Scenario Catalogue'!$B$2:$B$121,A9) | C9: =COUNTIF('Test Cases'!$B$2:$B$315,A9) | D9: =COUNTIFS('Test Cases'!$B$2:$B$315,$A9,'Test Cases'!$E$2:$E$315,"Positive") | E9: =COUNTIFS('Test Cases'!$B$2:$B$315,$A9,'Test Cases'!$E$2:$E$315,"Negative") | F9: =COUNTIFS('Test Cases'!$B$2:$B$315,$A9,'Test Cases'!$E$2:$E$315,"Boundary") | G9: =COUNTIFS('Test Cases'!$B$2:$B$315,$A9,'Test Cases'!$E$2:$E$315,"Edge") | H9: =COUNTIFS('Test Cases'!$B$2:$B$315,$A9,'Test Cases'!$J$2:$J$315,"Pass") | I9: =COUNTIFS('Test Cases'!$B$2:$B$315,$A9,'Test Cases'!$J$2:$J$315,"Fail") | J9: =COUNTIFS('Test Cases'!$B$2:$B$315,$A9,'Test Cases'!$J$2:$J$315,"Blocked") | K9: =COUNTIFS('Test Cases'!$B$2:$B$315,$A9,'Test Cases'!$J$2:$J$315,"Not Run") | L9: =IF(C9=0,0,(C9-K9)/C9) | M9: =IF((H9+I9+J9)=0,0,H9/(H9+I9+J9))
A10: Geographic & Impossible Travel | B10: =COUNTIF('Scenario Catalogue'!$B$2:$B$121,A10) | C10: =COUNTIF('Test Cases'!$B$2:$B$315,A10) | D10: =COUNTIFS('Test Cases'!$B$2:$B$315,$A10,'Test Cases'!$E$2:$E$315,"Positive") | E10: =COUNTIFS('Test Cases'!$B$2:$B$315,$A10,'Test Cases'!$E$2:$E$315,"Negative") | F10: =COUNTIFS('Test Cases'!$B$2:$B$315,$A10,'Test Cases'!$E$2:$E$315,"Boundary") | G10: =COUNTIFS('Test Cases'!$B$2:$B$315,$A10,'Test Cases'!$E$2:$E$315,"Edge") | H10: =COUNTIFS('Test Cases'!$B$2:$B$315,$A10,'Test Cases'!$J$2:$J$315,"Pass") | I10: =COUNTIFS('Test Cases'!$B$2:$B$315,$A10,'Test Cases'!$J$2:$J$315,"Fail") | J10: =COUNTIFS('Test Cases'!$B$2:$B$315,$A10,'Test Cases'!$J$2:$J$315,"Blocked") | K10: =COUNTIFS('Test Cases'!$B$2:$B$315,$A10,'Test Cases'!$J$2:$J$315,"Not Run") | L10: =IF(C10=0,0,(C10-K10)/C10) | M10: =IF((H10+I10+J10)=0,0,H10/(H10+I10+J10))
A11: Device, IP & Channel | B11: =COUNTIF('Scenario Catalogue'!$B$2:$B$121,A11) | C11: =COUNTIF('Test Cases'!$B$2:$B$315,A11) | D11: =COUNTIFS('Test Cases'!$B$2:$B$315,$A11,'Test Cases'!$E$2:$E$315,"Positive") | E11: =COUNTIFS('Test Cases'!$B$2:$B$315,$A11,'Test Cases'!$E$2:$E$315,"Negative") | F11: =COUNTIFS('Test Cases'!$B$2:$B$315,$A11,'Test Cases'!$E$2:$E$315,"Boundary") | G11: =COUNTIFS('Test Cases'!$B$2:$B$315,$A11,'Test Cases'!$E$2:$E$315,"Edge") | H11: =COUNTIFS('Test Cases'!$B$2:$B$315,$A11,'Test Cases'!$J$2:$J$315,"Pass") | I11: =COUNTIFS('Test Cases'!$B$2:$B$315,$A11,'Test Cases'!$J$2:$J$315,"Fail") | J11: =COUNTIFS('Test Cases'!$B$2:$B$315,$A11,'Test Cases'!$J$2:$J$315,"Blocked") | K11: =COUNTIFS('Test Cases'!$B$2:$B$315,$A11,'Test Cases'!$J$2:$J$315,"Not Run") | L11: =IF(C11=0,0,(C11-K11)/C11) | M11: =IF((H11+I11+J11)=0,0,H11/(H11+I11+J11))
A12: Behavioural Change & Profile Mismatch | B12: =COUNTIF('Scenario Catalogue'!$B$2:$B$121,A12) | C12: =COUNTIF('Test Cases'!$B$2:$B$315,A12) | D12: =COUNTIFS('Test Cases'!$B$2:$B$315,$A12,'Test Cases'!$E$2:$E$315,"Positive") | E12: =COUNTIFS('Test Cases'!$B$2:$B$315,$A12,'Test Cases'!$E$2:$E$315,"Negative") | F12: =COUNTIFS('Test Cases'!$B$2:$B$315,$A12,'Test Cases'!$E$2:$E$315,"Boundary") | G12: =COUNTIFS('Test Cases'!$B$2:$B$315,$A12,'Test Cases'!$E$2:$E$315,"Edge") | H12: =COUNTIFS('Test Cases'!$B$2:$B$315,$A12,'Test Cases'!$J$2:$J$315,"Pass") | I12: =COUNTIFS('Test Cases'!$B$2:$B$315,$A12,'Test Cases'!$J$2:$J$315,"Fail") | J12: =COUNTIFS('Test Cases'!$B$2:$B$315,$A12,'Test Cases'!$J$2:$J$315,"Blocked") | K12: =COUNTIFS('Test Cases'!$B$2:$B$315,$A12,'Test Cases'!$J$2:$J$315,"Not Run") | L12: =IF(C12=0,0,(C12-K12)/C12) | M12: =IF((H12+I12+J12)=0,0,H12/(H12+I12+J12))
A13: Cash-in / Cash-out | B13: =COUNTIF('Scenario Catalogue'!$B$2:$B$121,A13) | C13: =COUNTIF('Test Cases'!$B$2:$B$315,A13) | D13: =COUNTIFS('Test Cases'!$B$2:$B$315,$A13,'Test Cases'!$E$2:$E$315,"Positive") | E13: =COUNTIFS('Test Cases'!$B$2:$B$315,$A13,'Test Cases'!$E$2:$E$315,"Negative") | F13: =COUNTIFS('Test Cases'!$B$2:$B$315,$A13,'Test Cases'!$E$2:$E$315,"Boundary") | G13: =COUNTIFS('Test Cases'!$B$2:$B$315,$A13,'Test Cases'!$E$2:$E$315,"Edge") | H13: =COUNTIFS('Test Cases'!$B$2:$B$315,$A13,'Test Cases'!$J$2:$J$315,"Pass") | I13: =COUNTIFS('Test Cases'!$B$2:$B$315,$A13,'Test Cases'!$J$2:$J$315,"Fail") | J13: =COUNTIFS('Test Cases'!$B$2:$B$315,$A13,'Test Cases'!$J$2:$J$315,"Blocked") | K13: =COUNTIFS('Test Cases'!$B$2:$B$315,$A13,'Test Cases'!$J$2:$J$315,"Not Run") | L13: =IF(C13=0,0,(C13-K13)/C13) | M13: =IF((H13+I13+J13)=0,0,H13/(H13+I13+J13))
A14: Agent Network | B14: =COUNTIF('Scenario Catalogue'!$B$2:$B$121,A14) | C14: =COUNTIF('Test Cases'!$B$2:$B$315,A14) | D14: =COUNTIFS('Test Cases'!$B$2:$B$315,$A14,'Test Cases'!$E$2:$E$315,"Positive") | E14: =COUNTIFS('Test Cases'!$B$2:$B$315,$A14,'Test Cases'!$E$2:$E$315,"Negative") | F14: =COUNTIFS('Test Cases'!$B$2:$B$315,$A14,'Test Cases'!$E$2:$E$315,"Boundary") | G14: =COUNTIFS('Test Cases'!$B$2:$B$315,$A14,'Test Cases'!$E$2:$E$315,"Edge") | H14: =COUNTIFS('Test Cases'!$B$2:$B$315,$A14,'Test Cases'!$J$2:$J$315,"Pass") | I14: =COUNTIFS('Test Cases'!$B$2:$B$315,$A14,'Test Cases'!$J$2:$J$315,"Fail") | J14: =COUNTIFS('Test Cases'!$B$2:$B$315,$A14,'Test Cases'!$J$2:$J$315,"Blocked") | K14: =COUNTIFS('Test Cases'!$B$2:$B$315,$A14,'Test Cases'!$J$2:$J$315,"Not Run") | L14: =IF(C14=0,0,(C14-K14)/C14) | M14: =IF((H14+I14+J14)=0,0,H14/(H14+I14+J14))
A15: Merchant | B15: =COUNTIF('Scenario Catalogue'!$B$2:$B$121,A15) | C15: =COUNTIF('Test Cases'!$B$2:$B$315,A15) | D15: =COUNTIFS('Test Cases'!$B$2:$B$315,$A15,'Test Cases'!$E$2:$E$315,"Positive") | E15: =COUNTIFS('Test Cases'!$B$2:$B$315,$A15,'Test Cases'!$E$2:$E$315,"Negative") | F15: =COUNTIFS('Test Cases'!$B$2:$B$315,$A15,'Test Cases'!$E$2:$E$315,"Boundary") | G15: =COUNTIFS('Test Cases'!$B$2:$B$315,$A15,'Test Cases'!$E$2:$E$315,"Edge") | H15: =COUNTIFS('Test Cases'!$B$2:$B$315,$A15,'Test Cases'!$J$2:$J$315,"Pass") | I15: =COUNTIFS('Test Cases'!$B$2:$B$315,$A15,'Test Cases'!$J$2:$J$315,"Fail") | J15: =COUNTIFS('Test Cases'!$B$2:$B$315,$A15,'Test Cases'!$J$2:$J$315,"Blocked") | K15: =COUNTIFS('Test Cases'!$B$2:$B$315,$A15,'Test Cases'!$J$2:$J$315,"Not Run") | L15: =IF(C15=0,0,(C15-K15)/C15) | M15: =IF((H15+I15+J15)=0,0,H15/(H15+I15+J15))
A16: Reversals, Refunds & Failed Attempts | B16: =COUNTIF('Scenario Catalogue'!$B$2:$B$121,A16) | C16: =COUNTIF('Test Cases'!$B$2:$B$315,A16) | D16: =COUNTIFS('Test Cases'!$B$2:$B$315,$A16,'Test Cases'!$E$2:$E$315,"Positive") | E16: =COUNTIFS('Test Cases'!$B$2:$B$315,$A16,'Test Cases'!$E$2:$E$315,"Negative") | F16: =COUNTIFS('Test Cases'!$B$2:$B$315,$A16,'Test Cases'!$E$2:$E$315,"Boundary") | G16: =COUNTIFS('Test Cases'!$B$2:$B$315,$A16,'Test Cases'!$E$2:$E$315,"Edge") | H16: =COUNTIFS('Test Cases'!$B$2:$B$315,$A16,'Test Cases'!$J$2:$J$315,"Pass") | I16: =COUNTIFS('Test Cases'!$B$2:$B$315,$A16,'Test Cases'!$J$2:$J$315,"Fail") | J16: =COUNTIFS('Test Cases'!$B$2:$B$315,$A16,'Test Cases'!$J$2:$J$315,"Blocked") | K16: =COUNTIFS('Test Cases'!$B$2:$B$315,$A16,'Test Cases'!$J$2:$J$315,"Not Run") | L16: =IF(C16=0,0,(C16-K16)/C16) | M16: =IF((H16+I16+J16)=0,0,H16/(H16+I16+J16))
... A25: Engine Edge Cases (applies to all scenarios) | B25: =COUNTIF('Scenario Catalogue'!$B$2:$B$121,A25) | C25: =COUNTIF('Test Cases'!$B$2:$B$315,A25) | D25: =COUNTIFS('Test Cases'!$B$2:$B$315,$A25,'Test Cases'!$E$2:$E$315,"Positive") | E25: =COUNTIFS('Test Cases'!$B$2:$B$315,$A25,'Test Cases'!$E$2:$E$315,"Negative") | F25: =COUNTIFS('Test Cases'!$B$2:$B$315,$A25,'Test Cases'!$E$2:$E$315,"Boundary") | G25: =COUNTIFS('Test Cases'!$B$2:$B$315,$A25,'Test Cases'!$E$2:$E$315,"Edge") | H25: =COUNTIFS('Test Cases'!$B$2:$B$315,$A25,'Test Cases'!$J$2:$J$315,"Pass") | I25: =COUNTIFS('Test Cases'!$B$2:$B$315,$A25,'Test Cases'!$J$2:$J$315,"Fail") | J25: =COUNTIFS('Test Cases'!$B$2:$B$315,$A25,'Test Cases'!$J$2:$J$315,"Blocked") | K25: =COUNTIFS('Test Cases'!$B$2:$B$315,$A25,'Test Cases'!$J$2:$J$315,"Not Run") | L25: =IF(C25=0,0,(C25-K25)/C25) | M25: =IF((H25+I25+J25)=0,0,H25/(H25+I25+J25))
A26: Total | B26: =SUM(B5:B25) | C26: =SUM(C5:C25) | D26: =SUM(D5:D25) | E26: =SUM(E5:E25) | F26: =SUM(F5:F25) | G26: =SUM(G5:G25) | H26: =SUM(H5:H25) | I26: =SUM(I5:I25) | ... K26: =SUM(K5:K25) | L26: =IF(C26=0,0,(C26-K26)/C26) | M26: =IF((H26+I26+J26)=0,0,H26/(H26+I26+J26))

Sheet Scenario Catalogue
A1: Scenario ID | B1: Category | C1: Scenario | D1: Detection Logic | E1: Default Parameters (configurable) | F1: Alert Severity | G1: Priority | H1: # Test Cases
A2: VEL-01 | B2: Velocity & Frequency | C2: High count of cash withdrawals per day | D2: Count of completed cash-out/withdrawal transactions by the same customer within one calendar day (local time) ≥ N | E2: N=20 per day; channels=Agent, ATM; statuses counted=Completed | F2: High | G2: P1 | H2: =COUNTIF('Test Cases'!$C$2:$C$315,A2)
A3: VEL-02 | B3: Velocity & Frequency | C3: High count of withdrawals per hour (burst) | D3: Count of withdrawals within a rolling 60-minute window ≥ N | E3: N=8 per rolling hour | F3: High | G3: P1 | H3: =COUNTIF('Test Cases'!$C$2:$C$315,A3)
A4: VEL-03 | B4: Velocity & Frequency | C4: High count of outgoing P2P transfers per day | D4: Count of outgoing wallet-to-wallet transfers per customer per day ≥ N | E4: N=30 per day | F4: Medium | G4: P1 | H4: =COUNTIF('Test Cases'!$C$2:$C$315,A4)
A5: VEL-04 | B5: Velocity & Frequency | C5: High count of incoming transfers per day | D5: Count of incoming transfers to one customer per day ≥ N | E5: N=25 per day | F5: Medium | G5: P1 | H5: =COUNTIF('Test Cases'!$C$2:$C$315,A5)
A6: VEL-05 | B6: Velocity & Frequency | C6: Weekly transaction count spike | D6: Count of all financial transactions in a rolling 7 days ≥ N | E6: N=100 per 7 days (individual) | F6: Medium | G6: P2 | H6: =COUNTIF('Test Cases'!$C$2:$C$315,A6)
A7: VEL-06 | B7: Velocity & Frequency | C7: Many transactions within minutes of account opening | D7: Count of transactions within X hours after registration ≥ N | E7: X=24 hours; N=10 | F7: High | G7: P1 | H7: =COUNTIF('Test Cases'!$C$2:$C$315,A7)
A8: VEL-07 | B8: Velocity & Frequency | C8: Transactions at regular fixed intervals (automation) | D8: ≥ N transactions with near-identical time gaps (std-dev of gaps ≤ T seconds) | E8: N=10; T=5 seconds | F8: Medium | G8: P2 | H8: =COUNTIF('Test Cases'!$C$2:$C$315,A8)
A9: VEL-08 | B9: Velocity & Frequency | C9: High count of distinct channels in a day | D9: Number of distinct channels used (App, Agent, ATM, USSD, Web) in one day ≥ N with total amount ≥ A | E9: N=4; A=1,000 | F9: Low | G9: P3 | H9: =COUNTIF('Test Cases'!$C$2:$C$315,A9)
A10: AMT-01 | B10: Amount & Thresholds | C10: Single large transaction | D10: Single transaction amount ≥ threshold for customer type | E10: Individual 10,000; Corporate 50,000 (base currency) | F10: Medium | G10: P1 | H10: =COUNTIF('Test Cases'!$C$2:$C$315,A10)
A11: AMT-02 | B11: Amount & Thresholds | C11: Daily cumulative amount | D11: Sum of outgoing amounts per customer per calendar day ≥ A | E11: A=5,000 (individual) | F11: Medium | G11: P1 | H11: =COUNTIF('Test Cases'!$C$2:$C$315,A11)
A12: AMT-03 | B12: Amount & Thresholds | C12: Monthly cumulative amount vs declared income | D12: Monthly incoming amount > K × declared monthly income | E12: K=3 | F12: High | G12: P1 | H12: =COUNTIF('Test Cases'!$C$2:$C$315,A12)
A13: AMT-04 | B13: Amount & Thresholds | C13: Transaction amount vs expected activity in KYC | D13: Monthly volume exceeds expected monthly activity declared at onboarding by P% | E13: P=200% | F13: Medium | G13: P1 | H13: =COUNTIF('Test Cases'!$C$2:$C$315,A13)
... A121: ENG-12 | B121: Engine Edge Cases (applies to all scenarios) | C121: Performance at scale | D121: Windowed rules run on peak daily volume within target time | E121: Volume and target per NFR | F121: — | G121: P1 | H121: =COUNTIF('Test Cases'!$C$2:$C$315,A121)

Sheet Test Cases
A1: TC ID | B1: Category | C1: Scenario ID | D1: Scenario | E1: Test Type | F1: Test Description & Transaction Data | G1: Expected Result | H1: Alert Severity | I1: Priority | J1: Status | K1: Actual Result | L1: Tester | M1: Execution Date | N1: Defect ID | O1: Notes
A2: TM-VEL-01-01 | B2: Velocity & Frequency | C2: VEL-01 | D2: High count of cash withdrawals per day | E2: Positive | F2: C1 performs 20 cash withdrawals of 50 JOD at agents between 09:00 and 18:00 on the same day | G2: Alert raised on the 20th withdrawal; evidence lists all 20 transactions and the day window | H2: High | I2: P1 | J2: Pass | K2: 1 alert (ALR-202610-000146) triggered by the 20th withdrawal (V01A-369-19); 20 contributing transactions linked; evidence window 2025-01-03 21:00Z–2025-01-04 21:00Z. | L2: Claude (automated test suite) | M2: 2026-10-15 | O2: Automated: VelocityTests.VEL_01_cash_withdrawals_per_day
A3: TM-VEL-01-02 | B3: Velocity & Frequency | C3: VEL-01 | D3: High count of cash withdrawals per day | E3: Boundary | F3: C1 performs exactly 19 withdrawals in one day | G3: No alert | H3: High | I3: P1 | J3: Pass | K3: 19 withdrawals → 0 alerts. | L3: Claude (automated test suite) | M3: 2026-10-15 | O3: Automated: VelocityTests.VEL_01_cash_withdrawals_per_day
A4: TM-VEL-01-03 | B4: Velocity & Frequency | C4: VEL-01 | D4: High count of cash withdrawals per day | E4: Boundary | F4: 20 withdrawals where the 20th is at 23:59:59 local time | G4: Alert raised (same calendar day) | H4: High | I4: P1 | J4: Pass | K4: 20th withdrawal at 23:59:59 local → 1 alert (same calendar day 2025-01-03 21:00Z–2025-01-04 21:00Z). | L4: Claude (automated test suite) | M4: 2026-10-15 | O4: Automated: VelocityTests.VEL_01_cash_withdrawals_per_day
A5: TM-VEL-01-04 | B5: Velocity & Frequency | C5: VEL-01 | D5: High count of cash withdrawals per day | E5: Negative | F5: 10 withdrawals at 23:00–23:59 and 10 at 00:00–01:00 next day (local) | G5: No alert for daily calendar rule (two days of 10) | H5: High | I5: P1 | J5: Pass | K5: 10 withdrawals 23:00–23:45 and 10 on the next local day → 0 alerts (two calendar days of 10). | L5: Claude (automated test suite) | M5: 2026-10-15 | O5: Automated: VelocityTests.VEL_01_cash_withdrawals_per_day
A6: TM-VEL-01-05 | B6: Velocity & Frequency | C6: VEL-01 | D6: High count of cash withdrawals per day | E6: Negative | F6: 20 withdrawal attempts where 6 are Failed | G6: No alert (only 14 completed) | H6: High | I6: P1 | J6: Pass | K6: 20 attempts, 6 Failed → 14 completed counted → 0 alerts. | L6: Claude (automated test suite) | M6: 2026-10-15 | O6: Automated: VelocityTests.VEL_01_cash_withdrawals_per_day
A7: TM-VEL-01-06 | B7: Velocity & Frequency | C7: VEL-01 | D7: High count of cash withdrawals per day | E7: Edge | F7: 20 withdrawals, 3 later reversed | G7: Behaviour per configured netting policy; evidence shows reversals | H7: High | I7: P1 | J7: Pass | K7: Rule netting policy 'Exclude': 3 of 20 withdrawals reversed → 17 counted → 0 alerts (with policy 'Include' the reversed items would count). | L7: Claude (automated test suite) | M7: 2026-10-15 | O7: Automated: VelocityTests.VEL_01_cash_withdrawals_per_day
A8: TM-VEL-01-07 | B8: Velocity & Frequency | C8: VEL-01 | D8: High count of cash withdrawals per day | E8: Edge | F8: 20 withdrawals split across 2 wallets of the same customer | G8: Alert raised at customer level (aggregation by resolved customer) | H8: High | I8: P1 | J8: Pass | K8: 20 withdrawals split 10/10 across two wallets of the same customer → 1 customer-level alert. | L8: Claude (automated test suite) | M8: 2026-10-15 | O8: Automated: VelocityTests.VEL_01_cash_withdrawals_per_day
A9: TM-VEL-02-01 | B9: Velocity & Frequency | C9: VEL-02 | D9: High count of withdrawals per hour (burst) | E9: Positive | F9: C2 performs 8 ATM withdrawals of 100 JOD between 14:00 and 14:45 | G9: Alert raised; window boundaries in evidence | H9: High | I9: P1 | J9: Pass | K9: 8 ATM withdrawals 14:00–14:42 → 1 alert; rolling 60-min window boundaries in evidence. | L9: Claude (automated test suite) | M9: 2026-10-15 | O9: Automated: VelocityTests.VEL_02_withdrawal_burst_per_hour
A10: TM-VEL-02-02 | B10: Velocity & Frequency | C10: VEL-02 | D10: High count of withdrawals per hour (burst) | E10: Boundary | F10: 8 withdrawals spanning exactly 60 minutes 01 second | G10: No alert | H10: High | I10: P1 | J10: Pass | K10: 8 withdrawals spanning 60 min 01 s (window (t−60m, t]) → 0 alerts. | L10: Claude (automated test suite) | M10: 2026-10-15 | O10: Automated: VelocityTests.VEL_02_withdrawal_burst_per_hour
A11: TM-VEL-02-03 | B11: Velocity & Frequency | C11: VEL-02 | D11: High count of withdrawals per hour (burst) | E11: Negative | F11: 8 withdrawals spread evenly across 8 hours | G11: No alert for burst rule | H11: High | I11: P1 | J11: Pass | K11: 8 withdrawals one per hour → 0 alerts. | L11: Claude (automated test suite) | M11: 2026-10-15 | O11: Automated: VelocityTests.VEL_02_withdrawal_burst_per_hour
A12: TM-VEL-02-04 | B12: Velocity & Frequency | C12: VEL-02 | D12: High count of withdrawals per hour (burst) | E12: Edge | F12: Burst window crosses midnight (23:30–00:20) | G12: Alert raised (rolling window ignores calendar day) | H12: High | I12: P1 | J12: Pass | K12: Burst 23:30–00:19 local across midnight → 1 alert (rolling window ignores calendar day). | L12: Claude (automated test suite) | M12: 2026-10-15 | O12: Automated: VelocityTests.VEL_02_withdrawal_burst_per_hour
A13: TM-VEL-03-01 | B13: Velocity & Frequency | C13: VEL-03 | D13: High count of outgoing P2P transfers per day | E13: Positive | F13: C3 sends 30 P2P transfers of 10–40 JOD to various wallets in one day | G13: Alert raised | H13: Medium | I13: P1 | J13: Pass | K13: 30 P2P transfers (10–40 JOD) in one day → 1 alert. | L13: Claude (automated test suite) | M13: 2026-10-15 | O13: Automated: VelocityTests.VEL_03_outgoing_p2p_per_day
A14: TM-VEL-03-02 | B14: Velocity & Frequency | C14: VEL-03 | D14: High count of outgoing P2P transfers per day | E14: Boundary | F14: 29 transfers | G14: No alert | H14: Medium | I14: P1 | J14: Pass | K14: 29 transfers → 0 alerts. | L14: Claude (automated test suite) | M14: 2026-10-15 | O14: Automated: VelocityTests.VEL_03_outgoing_p2p_per_day
A15: TM-VEL-03-03 | B15: Velocity & Frequency | C15: VEL-03 | D15: High count of outgoing P2P transfers per day | E15: Negative | F15: 30 transfers where 15 are to the customer's own second wallet | G15: Own-account transfers excluded per configuration; no alert | H15: Medium | I15: P1 | J15: Pass | K15: 30 transfers of which 15 to the customer's own second wallet → 0 alert(s). Own-account transfers excluded by the rule filter txn.isOwnAccount = false (15 counted). | L15: Claude (automated test suite) | M15: 2026-10-15 | N15: DEF-TM-01 (fixed) | O15: Automated: VelocityTests.VEL_03_outgoing_p2p_per_day. Failed in the first execution (DEF-TM-01: Own-wallet / self-transfer exclusion not configurable); fixed: Rule field txn.isOwnAccount; re-tested 2026-10-15.
A16: TM-VEL-03-04 | B16: Velocity & Frequency | C16: VEL-03 | D16: High count of outgoing P2P transfers per day | E16: Edge | F16: Customer type = Merchant with higher configured threshold (N=200) | G16: No alert at 30 | H16: Medium | I16: P1 | J16: Pass | K16: Merchant with 30 transfers: individual rule scoped out, merchant rule threshold 200 → 0 alerts. | L16: Claude (automated test suite) | M16: 2026-10-15 | O16: Automated: VelocityTests.VEL_03_outgoing_p2p_per_day
A17: TM-VEL-04-01 | B17: Velocity & Frequency | C17: VEL-04 | D17: High count of incoming transfers per day | E17: Positive | F17: C4 receives 25 transfers of 20 JOD from different senders in one day | G17: Alert raised | H17: Medium | I17: P1 | J17: Pass | K17: 25 incoming transfers of 20 from different senders → 1 alert. | L17: Claude (automated test suite) | M17: 2026-10-15 | O17: Automated: VelocityTests.VEL_04_incoming_per_day
A18: TM-VEL-04-02 | B18: Velocity & Frequency | C18: VEL-04 | D18: High count of incoming transfers per day | E18: Boundary | F18: 24 incoming transfers | G18: No alert | H18: Medium | I18: P1 | J18: Pass | K18: 24 incoming → 0 alerts. | L18: Claude (automated test suite) | M18: 2026-10-15 | O18: Automated: VelocityTests.VEL_04_incoming_per_day
A19: TM-VEL-04-03 | B19: Velocity & Frequency | C19: VEL-04 | D19: High count of incoming transfers per day | E19: Negative | F19: 25 incoming refunds from a merchant | G19: Refunds excluded per configuration; no alert | H19: Medium | I19: P1 | J19: Pass | K19: 25 incoming merchant refunds excluded by type filter → 0 alerts. | L19: Claude (automated test suite) | M19: 2026-10-15 | O19: Automated: VelocityTests.VEL_04_incoming_per_day
A20: TM-VEL-04-04 | B20: Velocity & Frequency | C20: VEL-04 | D20: High count of incoming transfers per day | E20: Edge | F20: Incoming salary bulk payment counted as one batch | G20: Counted once; no alert | H20: Medium | I20: P1 | J20: Pass | K20: Salary bulk payment ingested as one batch record → counted once → 0 alerts. | L20: Claude (automated test suite) | M20: 2026-10-15 | O20: Automated: VelocityTests.VEL_04_incoming_per_day
A21: TM-VEL-05-01 | B21: Velocity & Frequency | C21: VEL-05 | D21: Weekly transaction count spike | E21: Positive | F21: C5 performs 101 transactions of mixed types in 6 days | G21: Alert raised | H21: Medium | I21: P2 | J21: Pass | K21: 101 mixed transactions in ~5.6 days → 1 alert(s). | L21: Claude (automated test suite) | M21: 2026-10-15 | O21: Automated: VelocityTests.VEL_05_weekly_count
A22: TM-VEL-05-02 | B22: Velocity & Frequency | C22: VEL-05 | D22: Weekly transaction count spike | E22: Boundary | F22: 100 transactions in 7 days | G22: Alert raised (≥) | H22: Medium | I22: P2 | J22: Pass | K22: Exactly 100 transactions within 6.9 days → 1 alert (≥). | L22: Claude (automated test suite) | M22: 2026-10-15 | O22: Automated: VelocityTests.VEL_05_weekly_count
A23: TM-VEL-05-03 | B23: Velocity & Frequency | C23: VEL-05 | D23: Weekly transaction count spike | E23: Negative | F23: 100 transactions over 8 days | G23: No alert | H23: Medium | I23: P2 | J23: Pass | K23: 100 transactions spread over 8 days → 0 alerts. | L23: Claude (automated test suite) | M23: 2026-10-15 | O23: Automated: VelocityTests.VEL_05_weekly_count
A24: TM-VEL-05-04 | B24: Velocity & Frequency | C24: VEL-05 | D24: Weekly transaction count spike | E24: Edge | F24: Rule applicability excludes corporate customers; corporate with 150 | G24: No alert | H24: Medium | I24: P2 | J24: Pass | K24: Corporate with 150 in a week, rule scoped to individuals → 0 alerts. | L24: Claude (automated test suite) | M24: 2026-10-15 | O24: Automated: VelocityTests.VEL_05_weekly_count
A25: TM-VEL-06-01 | B25: Velocity & Frequency | C25: VEL-06 | D25: Many transactions within minutes of account opening | E25: Positive | F25: New wallet registered 10:00; 10 transactions by 18:00 same day | G25: Alert raised; account age in evidence | H25: High | I25: P1 | J25: Pass | K25: Wallet registered on the day, 10 transactions 10:30–17:15 → 1 alert; account age (customer.accountAgeDays = 0) in the matched conditions. | L25: Claude (automated test suite) | M25: 2026-10-15 | O25: Automated: ExtendedCapabilityTests.VEL_06_activity_right_after_registration. Blocked in the first execution (capability gap); executable after the rule DSL extension.
A26: TM-VEL-06-02 | B26: Velocity & Frequency | C26: VEL-06 | D26: Many transactions within minutes of account opening | E26: Boundary | F26: 10th transaction at 24h 01m after registration | G26: No alert | H26: High | I26: P1 | J26: Pass | K26: 9 transactions from 10:00 and the 10th at 24 h 01 m → 0 alerts (rolling 24 h window). | L26: Claude (automated test suite) | M26: 2026-10-15 | O26: Automated: ExtendedCapabilityTests.VEL_06_activity_right_after_registration. Note: registration is stored as a date, so account age has day (not minute) precision.. Blocked in the first execution (capability gap); executable after the rule DSL extension.
A27: TM-VEL-06-03 | B27: Velocity & Frequency | C27: VEL-06 | D27: Many transactions within minutes of account opening | E27: Negative | F27: Existing 2-year-old customer does 10 transactions in a day | G27: Rule not applicable; no alert | H27: High | I27: P1 | J27: Pass | K27: Two-year-old customer with 10 transactions in a day → 0 alerts. | L27: Claude (automated test suite) | M27: 2026-10-15 | O27: Automated: ExtendedCapabilityTests.VEL_06_activity_right_after_registration. Blocked in the first execution (capability gap); executable after the rule DSL extension.
A28: TM-VEL-06-04 | B28: Velocity & Frequency | C28: VEL-06 | D28: Many transactions within minutes of account opening | E28: Edge | F28: Registration timestamp missing | G28: Data-quality issue raised; rule records unable-to-evaluate, not silent pass | H28: High | I28: P1 | J28: Pass | K28: Registration date missing → no silent pass: condition not met and data-quality item "[R_9215E93CF89D/customer.accountAgeDays] Rule R_9215E93CF89D v1 could not evaluate 'customer.accountAgeDays' for customer 105: value missing; condition treated as not met (result incomplete). Complete the customer data.". | L28: Claude (automated test suite) | M28: 2026-10-15 | O28: Automated: ExtendedCapabilityTests.VEL_06_activity_right_after_registration. Blocked in the first execution (capability gap); executable after the rule DSL extension.
A29: TM-VEL-07-01 | B29: Velocity & Frequency | C29: VEL-07 | D29: Transactions at regular fixed intervals (automation) | E29: Positive | F29: 12 transfers exactly every 60 seconds (±2s) | G29: Alert raised as possible scripted activity | H29: Medium | I29: P2 | J29: Blocked | K29: Capability gap — No aggregate for regularity of time gaps (standard deviation of inter-transaction intervals). Closest rule definition rejected by the rule validator: $.condition.aggregate: Unknown aggregate 'intervalStdDev'. Allowed: count, sum, distinctCounterparties, ratio, rapidMovement, dormancyDays, profileRatio, peerRatio, newCustomers, customersPerDevice, cycle, newCountries, historyCount, historySum, historyRatio, distinctCount, reciprocalCount, consecutiveDays, newCounterpartyShare, sharedDeviceSenders, typeShareChange, minutesSinceEvent.. | L29: Claude (automated test suite) | M29: 2026-10-15 | N29: GAP-VEL-07 | O29: Automated: CapabilityGapTests.Scenario_not_configurable (rule validator evidence)
A30: TM-VEL-07-02 | B30: Velocity & Frequency | C30: VEL-07 | D30: Transactions at regular fixed intervals (automation) | E30: Negative | F30: 12 transfers at random intervals | G30: No alert | H30: Medium | I30: P2 | J30: Blocked | K30: Capability gap — No aggregate for regularity of time gaps (standard deviation of inter-transaction intervals). Closest rule definition rejected by the rule validator: $.condition.aggregate: Unknown aggregate 'intervalStdDev'. Allowed: count, sum, distinctCounterparties, ratio, rapidMovement, dormancyDays, profileRatio, peerRatio, newCustomers, customersPerDevice, cycle, newCountries, historyCount, historySum, historyRatio, distinctCount, reciprocalCount, consecutiveDays, newCounterpartyShare, sharedDeviceSenders, typeShareChange, minutesSinceEvent.. | L30: Claude (automated test suite) | M30: 2026-10-15 | N30: GAP-VEL-07 | O30: Automated: CapabilityGapTests.Scenario_not_configurable (rule validator evidence)
A31: TM-VEL-07-03 | B31: Velocity & Frequency | C31: VEL-07 | D31: Transactions at regular fixed intervals (automation) | E31: Boundary | F31: 9 regular transfers | G31: No alert | H31: Medium | I31: P2 | J31: Blocked | K31: Capability gap — No aggregate for regularity of time gaps (standard deviation of inter-transaction intervals). Closest rule definition rejected by the rule validator: $.condition.aggregate: Unknown aggregate 'intervalStdDev'. Allowed: count, sum, distinctCounterparties, ratio, rapidMovement, dormancyDays, profileRatio, peerRatio, newCustomers, customersPerDevice, cycle, newCountries, historyCount, historySum, historyRatio, distinctCount, reciprocalCount, consecutiveDays, newCounterpartyShare, sharedDeviceSenders, typeShareChange, minutesSinceEvent.. | L31: Claude (automated test suite) | M31: 2026-10-15 | N31: GAP-VEL-07 | O31: Automated: CapabilityGapTests.Scenario_not_configurable (rule validator evidence)
A32: TM-VEL-07-04 | B32: Velocity & Frequency | C32: VEL-07 | D32: Transactions at regular fixed intervals (automation) | E32: Edge | F32: Scheduled standing order configured by customer | G32: Excluded by transaction sub-type; no alert | H32: Medium | I32: P2 | J32: Blocked | K32: Capability gap — No aggregate for regularity of time gaps (standard deviation of inter-transaction intervals). Closest rule definition rejected by the rule validator: $.condition.aggregate: Unknown aggregate 'intervalStdDev'. Allowed: count, sum, distinctCounterparties, ratio, rapidMovement, dormancyDays, profileRatio, peerRatio, newCustomers, customersPerDevice, cycle, newCountries, historyCount, historySum, historyRatio, distinctCount, reciprocalCount, consecutiveDays, newCounterpartyShare, sharedDeviceSenders, typeShareChange, minutesSinceEvent.. | L32: Claude (automated test suite) | M32: 2026-10-15 | N32: GAP-VEL-07 | O32: Automated: CapabilityGapTests.Scenario_not_configurable (rule validator evidence)
A33: TM-VEL-08-01 | B33: Velocity & Frequency | C33: VEL-08 | D33: High count of distinct channels in a day | E33: Positive | F33: C6 uses App, Agent, ATM and Web on same day totalling 1,500 | G33: Alert raised | H33: Low | I33: P3 | J33: Pass | K33: App, Agent, ATM and Web on one day totalling 1,500 → 1 alert (distinctCount of channel). | L33: Claude (automated test suite) | M33: 2026-10-15 | O33: Automated: ExtendedCapabilityTests.VEL_08_many_channels. Blocked in the first execution (capability gap); executable after the rule DSL extension.
A34: TM-VEL-08-02 | B34: Velocity & Frequency | C34: VEL-08 | D34: High count of distinct channels in a day | E34: Negative | F34: 4 channels but total 300 | G34: No alert | H34: Low | I34: P3 | J34: Pass | K34: 4 channels, total 300 → 0 alerts. | L34: Claude (automated test suite) | M34: 2026-10-15 | O34: Automated: ExtendedCapabilityTests.VEL_08_many_channels. Blocked in the first execution (capability gap); executable after the rule DSL extension.
A35: TM-VEL-08-03 | B35: Velocity & Frequency | C35: VEL-08 | D35: High count of distinct channels in a day | E35: Boundary | F35: 3 channels, 2,000 total | G35: No alert | H35: Low | I35: P3 | J35: Pass | K35: 3 channels, total 2,100 → 0 alerts. | L35: Claude (automated test suite) | M35: 2026-10-15 | O35: Automated: ExtendedCapabilityTests.VEL_08_many_channels. Blocked in the first execution (capability gap); executable after the rule DSL extension.
A36: TM-AMT-01-01 | B36: Amount & Thresholds | C36: AMT-01 | D36: Single large transaction | E36: Positive | F36: Individual C7 sends 10,000 JOD transfer | G36: Alert raised | H36: Medium | I36: P1 | J36: Pass | K36: Individual 10,000 JOD transfer → 1 alert. | L36: Claude (automated test suite) | M36: 2026-10-15 | O36: Automated: AmountTests.AMT_01_single_large_transaction
A37: TM-AMT-01-02 | B37: Amount & Thresholds | C37: AMT-01 | D37: Single large transaction | E37: Boundary | F37: 9,999.999 JOD | G37: No alert | H37: Medium | I37: P1 | J37: Pass | K37: 9,999.999 JOD → 0 alerts (decimal precision preserved). | L37: Claude (automated test suite) | M37: 2026-10-15 | O37: Automated: AmountTests.AMT_01_single_large_transaction
A38: TM-AMT-01-03 | B38: Amount & Thresholds | C38: AMT-01 | D38: Single large transaction | E38: Positive | F38: 15,000 USD equivalent ≥ threshold after FX conversion | G38: Alert raised; FX rate in evidence | H38: Medium | I38: P1 | J38: Pass | K38: 15,000 USD → base 10,635 JOD → 1 alert; FX rate 0.709 and date in evidence. | L38: Claude (automated test suite) | M38: 2026-10-15 | O38: Automated: AmountTests.AMT_01_single_large_transaction
A39: TM-AMT-01-04 | B39: Amount & Thresholds | C39: AMT-01 | D39: Single large transaction | E39: Negative | F39: Corporate sends 20,000 | G39: No alert (corporate threshold) | H39: Medium | I39: P1 | J39: Pass | K39: Corporate 20,000 (corporate threshold 50,000) → 0 alerts. | L39: Claude (automated test suite) | M39: 2026-10-15 | O39: Automated: AmountTests.AMT_01_single_large_transaction
A40: TM-AMT-01-05 | B40: Amount & Thresholds | C40: AMT-01 | D40: Single large transaction | E40: Edge | F40: Transaction Pending then Completed | G40: Alert only once, at configured status | H40: Medium | I40: P1 | J40: Pass | K40: While Pending: 0 alerts; after status update to Completed and two reruns: 1 alert (raised once, at configured status). | L40: Claude (automated test suite) | M40: 2026-10-15 | O40: Automated: AmountTests.AMT_01_single_large_transaction
A41: TM-AMT-02-01 | B41: Amount & Thresholds | C41: AMT-02 | D41: Daily cumulative amount | E41: Positive | F41: 5 transfers of 1,000 each on same day | G41: Alert raised on 5th | H41: Medium | I41: P1 | J41: Pass | K41: 5 × 1,000 same day → 1 alert raised on the 5th transfer. | L41: Claude (automated test suite) | M41: 2026-10-15 | O41: Automated: AmountTests.AMT_02_daily_cumulative
A42: TM-AMT-02-02 | B42: Amount & Thresholds | C42: AMT-02 | D42: Daily cumulative amount | E42: Boundary | F42: Total 4,999.99 | G42: No alert | H42: Medium | I42: P1 | J42: Pass | K42: Total 4,999.99 → 0 alerts. | L42: Claude (automated test suite) | M42: 2026-10-15 | O42: Automated: AmountTests.AMT_02_daily_cumulative
A43: TM-AMT-02-03 | B43: Amount & Thresholds | C43: AMT-02 | D43: Daily cumulative amount | E43: Negative | F43: 3,000 on day 1 and 3,000 on day 2 | G43: No alert for daily rule | H43: Medium | I43: P1 | J43: Pass | K43: 3,000 on day 1 and 3,000 on day 2 → 0 alerts. | L43: Claude (automated test suite) | M43: 2026-10-15 | O43: Automated: AmountTests.AMT_02_daily_cumulative
A44: TM-AMT-02-04 | B44: Amount & Thresholds | C44: AMT-02 | D44: Daily cumulative amount | E44: Edge | F44: Mixed currencies 2,000 JOD + 4,300 USD | G44: Converted to JOD; alert if ≥ 5,000 | H44: Medium | I44: P1 | J44: Pass | K44: 2,000 JOD + 4,300 USD (=3,048.70 JOD at 0.709) = 5,048.70 JOD → 1 alert. | L44: Claude (automated test suite) | M44: 2026-10-15 | O44: Automated: AmountTests.AMT_02_daily_cumulative
... A47: TM-AMT-03-03 | B47: Amount & Thresholds | C47: AMT-03 | D47: Monthly cumulative amount vs declared income | E47: Negative | F47: Declared income 2,000; receives 4,000 | G47: No alert | H47: High | I47: P1 | J47: Pass | K47: Income 2,000, received 4,000 (2×) → 0 alerts. | L47: Claude (automated test suite) | M47: 2026-10-15 | O47: Automated: AmountTests.AMT_03_monthly_income_multiple
A48: TM-AMT-03-04 | B48: Amount & Thresholds | C48: AMT-03 | D48: Monthly cumulative amount vs declared income | E48: Edge | F48: Declared income missing | G48: Missing data recorded; alert type 'profile incomplete' per configuration, not silent pass | H48: High | I48: P1 | J48: Pass | K48: Declared income missing → 0 alerts; condition treated as not met and data-quality item raised: "[R_9D2264D830AF/profile.declaredMonthlyIncome] Rule R_9D2264D830AF v1 could not evaluate 'profile.declaredMonthlyIncome' for customer 404: value missing; condition treated as not met (result incomplete). Complete the customer data." (execution status Succeeded). | L48: Claude (automated test suite) | M48: 2026-10-15 | N48: DEF-TM-02 (fixed) | O48: Automated: AmountTests.AMT_03_monthly_income_multiple. Failed in the first execution (DEF-TM-02: Missing profile/attribute data silently evaluated as no-match); fixed: Missing inputs raise RuleInputMissing data-quality items (result incomplete); re-tested 2026-10-15.
A49: TM-AMT-03-05 | B49: Amount & Thresholds | C49: AMT-03 | D49: Monthly cumulative amount vs declared income | E49: Edge | F49: Income updated mid-month | G49: Uses effective-dated value per documented rule | H49: High | I49: P1 | J49: Pass | K49: Income changed 500→2,000 on 15 Mar; 1,600 received → evaluated against the value effective at each transaction time (documented rule) → 1,600/2,000 = 0.8 at month total → 0 alerts. | L49: Claude (automated test suite) | M49: 2026-10-15 | O49: Automated: AmountTests.AMT_03_monthly_income_multiple
A50: TM-AMT-04-01 | B50: Amount & Thresholds | C50: AMT-04 | D50: Transaction amount vs expected activity in KYC | E50: Positive | F50: Expected 1,000/month; actual 3,100 | G50: Alert raised | H50: Medium | I50: P1 | J50: Pass | K50: Expected 1,000/month, actual 3,100 (>200% above) → 1 alert. | L50: Claude (automated test suite) | M50: 2026-10-15 | O50: Automated: AmountTests.AMT_04_expected_activity
A51: TM-AMT-04-02 | B51: Amount & Thresholds | C51: AMT-04 | D51: Transaction amount vs expected activity in KYC | E51: Boundary | F51: Actual 3,000 | G51: No alert (200% exactly is not exceeded) | H51: Medium | I51: P1 | J51: Pass | K51: Actual 3,000 (exactly 200% above, not exceeded) → 0 alerts. | L51: Claude (automated test suite) | M51: 2026-10-15 | O51: Automated: AmountTests.AMT_04_expected_activity
A52: TM-AMT-04-03 | B52: Amount & Thresholds | C52: AMT-04 | D52: Transaction amount vs expected activity in KYC | E52: Negative | F52: Actual 2,500 | G52: No alert | H52: Medium | I52: P1 | J52: Pass | K52: Actual 2,500 → 0 alerts. | L52: Claude (automated test suite) | M52: 2026-10-15 | O52: Automated: AmountTests.AMT_04_expected_activity
A53: TM-AMT-04-04 | B53: Amount & Thresholds | C53: AMT-04 | D53: Transaction amount vs expected activity in KYC | E53: Edge | F53: Customer with EDD and approved higher expectation | G53: Uses latest approved expectation | H53: Medium | I53: P1 | J53: Pass | K53: EDD-approved higher expectation 5,000 (latest effective profile) used; 3,100 → 0 alerts. | L53: Claude (automated test suite) | M53: 2026-10-15 | O53: Automated: AmountTests.AMT_04_expected_activity
A54: TM-AMT-05-01 | B54: Amount & Thresholds | C54: AMT-05 | D54: Deviation from own historical average | E54: Positive | F54: Average weekly outflow 200; this week 1,200 | G54: Alert raised; baseline in evidence | H54: Medium | I54: P1 | J54: Pass | K54: Average weekly outflow 200 (12 weeks), this week 1,200 (6×) → 1 alert; baseline (historical average, history sum, lookback) in evidence. | L54: Claude (automated test suite) | M54: 2026-10-15 | O54: Automated: ExtendedCapabilityTests.AMT_05_deviation_from_own_average. Blocked in the first execution (capability gap); executable after the rule DSL extension.
A55: TM-AMT-05-02 | B55: Amount & Thresholds | C55: AMT-05 | D55: Deviation from own historical average | E55: Boundary | F55: This week 1,000 (exactly 5×) | G55: Alert per ≥ configuration | H55: Medium | I55: P1 | J55: Pass | K55: This week 1,000 = exactly 5× → 1 alert (operator gte). | L55: Claude (automated test suite) | M55: 2026-10-15 | O55: Automated: ExtendedCapabilityTests.AMT_05_deviation_from_own_average. Blocked in the first execution (capability gap); executable after the rule DSL extension.
A56: TM-AMT-05-03 | B56: Amount & Thresholds | C56: AMT-05 | D56: Deviation from own historical average | E56: Negative | F56: Customer with 10 days of history | G56: Rule not applied (insufficient history); recorded as not evaluated | H56: Medium | I56: P1 | J56: Pass | K56: Customer with 10 days of history and a 2,000 week → 0 alerts; rule applicability (accountAgeDays ≥ 30) not met, recorded in the execution result as not applicable: True. | L56: Claude (automated test suite) | M56: 2026-10-15 | O56: Automated: ExtendedCapabilityTests.AMT_05_deviation_from_own_average. Blocked in the first execution (capability gap); executable after the rule DSL extension.
A57: TM-AMT-05-04 | B57: Amount & Thresholds | C57: AMT-05 | D57: Deviation from own historical average | E57: Edge | F57: Baseline 0 (no prior activity) | G57: No divide-by-zero; handled by dormant rule instead | H57: Medium | I57: P1 | J57: Pass | K57: Baseline 0 (no prior activity), 2,000 this week → 0 alerts; ratio undefined (no divide-by-zero, execution succeeded); first-time activity is covered by the dormancy/new-account rules. | L57: Claude (automated test suite) | M57: 2026-10-15 | O57: Automated: ExtendedCapabilityTests.AMT_05_deviation_from_own_average. Blocked in the first execution (capability gap); executable after the rule DSL extension.
A58: TM-AMT-06-01 | B58: Amount & Thresholds | C58: AMT-06 | D58: Deviation from peer group | E58: Positive | F58: Student segment customer at 99.5th percentile of monthly volume | G58: Alert raised; peer statistics in evidence | H58: Medium | I58: P2 | J58: Blocked | K58: Capability gap — peerRatio compares with the peer median of agent-processed volume only; no percentile, segment or minimum peer-group size. Closest rule definition rejected by the rule validator: $.condition.aggregate: Unknown aggregate 'peerPercentile'. Allowed: count, sum, distinctCounterparties, ratio, rapidMovement, dormancyDays, profileRatio, peerRatio, newCustomers, customersPerDevice, cycle, newCountries, historyCount, historySum, historyRatio, distinctCount, reciprocalCount, consecutiveDays, newCounterpartyShare, sharedDeviceSenders, typeShareChange, minutesSinceEvent.. | L58: Claude (automated test suite) | M58: 2026-10-15 | N58: GAP-AMT-06 | O58: Automated: CapabilityGapTests.Scenario_not_configurable (rule validator evidence)
A59: TM-AMT-06-02 | B59: Amount & Thresholds | C59: AMT-06 | D59: Deviation from peer group | E59: Negative | F59: Customer at 95th percentile | G59: No alert | H59: Medium | I59: P2 | J59: Blocked | K59: Capability gap — peerRatio compares with the peer median of agent-processed volume only; no percentile, segment or minimum peer-group size. Closest rule definition rejected by the rule validator: $.condition.aggregate: Unknown aggregate 'peerPercentile'. Allowed: count, sum, distinctCounterparties, ratio, rapidMovement, dormancyDays, profileRatio, peerRatio, newCustomers, customersPerDevice, cycle, newCountries, historyCount, historySum, historyRatio, distinctCount, reciprocalCount, consecutiveDays, newCounterpartyShare, sharedDeviceSenders, typeShareChange, minutesSinceEvent.. | L59: Claude (automated test suite) | M59: 2026-10-15 | N59: GAP-AMT-06 | O59: Automated: CapabilityGapTests.Scenario_not_configurable (rule validator evidence)
A60: TM-AMT-06-03 | B60: Amount & Thresholds | C60: AMT-06 | D60: Deviation from peer group | E60: Edge | F60: Peer group has 20 members | G60: Rule not evaluated; logged | H60: Medium | I60: P2 | J60: Blocked | K60: Capability gap — peerRatio compares with the peer median of agent-processed volume only; no percentile, segment or minimum peer-group size. Closest rule definition rejected by the rule validator: $.condition.aggregate: Unknown aggregate 'peerPercentile'. Allowed: count, sum, distinctCounterparties, ratio, rapidMovement, dormancyDays, profileRatio, peerRatio, newCustomers, customersPerDevice, cycle, newCountries, historyCount, historySum, historyRatio, distinctCount, reciprocalCount, consecutiveDays, newCounterpartyShare, sharedDeviceSenders, typeShareChange, minutesSinceEvent.. | L60: Claude (automated test suite) | M60: 2026-10-15 | N60: GAP-AMT-06 | O60: Automated: CapabilityGapTests.Scenario_not_configurable (rule validator evidence)
A61: TM-AMT-07-01 | B61: Amount & Thresholds | C61: AMT-07 | D61: Round-amount transactions | E61: Positive | F61: Transfers of 500, 1,000, 700, 900, 300 within 5 days | G61: Alert raised | H61: Low | I61: P2 | J61: Pass | K61: 500, 1,000, 700, 900, 300 within 5 days → 1 alert (operator multipleOf 100). | L61: Claude (automated test suite) | M61: 2026-10-15 | O61: Automated: ExtendedCapabilityTests.AMT_07_round_amounts. Blocked in the first execution (capability gap); executable after the rule DSL extension.
A62: TM-AMT-07-02 | B62: Amount & Thresholds | C62: AMT-07 | D62: Round-amount transactions | E62: Negative | F62: Transfers of 503.25, 1,012.10 etc. | G62: No alert | H62: Low | I62: P2 | J62: Pass | K62: 503.25, 1,012.10, ... → 0 alerts. | L62: Claude (automated test suite) | M62: 2026-10-15 | O62: Automated: ExtendedCapabilityTests.AMT_07_round_amounts. Blocked in the first execution (capability gap); executable after the rule DSL extension.
A63: TM-AMT-07-03 | B63: Amount & Thresholds | C63: AMT-07 | D63: Round-amount transactions | E63: Boundary | F63: 4 round transfers | G63: No alert | H63: Low | I63: P2 | J63: Pass | K63: 4 round transfers → 0 alerts. | L63: Claude (automated test suite) | M63: 2026-10-15 | O63: Automated: ExtendedCapabilityTests.AMT_07_round_amounts. Blocked in the first execution (capability gap); executable after the rule DSL extension.
A64: TM-AMT-08-01 | B64: Amount & Thresholds | C64: AMT-08 | D64: Large transaction on low-risk product | E64: Positive | F64: Basic-KYC wallet receives 1,200 (core failed to enforce limit) | G64: Alert raised as limit breach | H64: High | I64: P1 | J64: Pass | K64: Basic-KYC wallet received 1,200 (> product limit 1,000) → 1 limit-breach alert. | L64: Claude (automated test suite) | M64: 2026-10-15 | O64: Automated: AmountTests.AMT_08_basic_kyc_limit
A65: TM-AMT-08-02 | B65: Amount & Thresholds | C65: AMT-08 | D65: Large transaction on low-risk product | E65: Negative | F65: Full-KYC wallet receives 1,200 | G65: No alert | H65: High | I65: P1 | J65: Pass | K65: Full-KYC wallet received 1,200 → 0 alerts. | L65: Claude (automated test suite) | M65: 2026-10-15 | O65: Automated: AmountTests.AMT_08_basic_kyc_limit
A66: TM-AMT-08-03 | B66: Amount & Thresholds | C66: AMT-08 | D66: Large transaction on low-risk product | E66: Edge | F66: Wallet upgraded to full KYC 1 hour before transaction | G66: Uses KYC level at transaction time | H66: High | I66: P1 | J66: Pass | K66: Wallet upgraded 1 h before the transaction; KYC level evaluated as of transaction time (effective-dated field) → 0 alerts. | L66: Claude (automated test suite) | M66: 2026-10-15 | O66: Automated: AmountTests.AMT_08_basic_kyc_limit
A67: TM-STR-01-01 | B67: Structuring & Smurfing | C67: STR-01 | D67: Multiple transactions just below threshold | E67: Positive | F67: Three deposits of 9,500, 9,800 and 9,900 within 4 days | G67: Alert raised; structuring indicator | H67: High | I67: P1 | J67: Pass | K67: 9,500 / 9,800 / 9,900 within 4 days → 1 structuring alert. | L67: Claude (automated test suite) | M67: 2026-10-15 | O67: Automated: StructuringTests.STR_01_below_threshold
A68: TM-STR-01-02 | B68: Structuring & Smurfing | C68: STR-01 | D68: Multiple transactions just below threshold | E68: Boundary | F68: Two deposits in band and one of 8,999 | G68: No alert | H68: High | I68: P1 | J68: Pass | K68: Two in band + 8,999 → 0 alerts. | L68: Claude (automated test suite) | M68: 2026-10-15 | O68: Automated: StructuringTests.STR_01_below_threshold
A69: TM-STR-01-03 | B69: Structuring & Smurfing | C69: STR-01 | D69: Multiple transactions just below threshold | E69: Boundary | F69: Amount exactly 9,000 (90%) | G69: Counted (inclusive lower bound) | H69: High | I69: P1 | J69: Pass | K69: 9,000 (exactly 90%) counted (inclusive lower bound) with two others → 1 alert. | L69: Claude (automated test suite) | M69: 2026-10-15 | O69: Automated: StructuringTests.STR_01_below_threshold
A70: TM-STR-01-04 | B70: Structuring & Smurfing | C70: STR-01 | D70: Multiple transactions just below threshold | E70: Negative | F70: Three deposits of 10,500 | G70: Not structuring; single large rule handles them | H70: High | I70: P1 | J70: Pass | K70: Three deposits of 10,500 → 0 structuring alerts (handled by single-large rule). | L70: Claude (automated test suite) | M70: 2026-10-15 | O70: Automated: StructuringTests.STR_01_below_threshold
A71: TM-STR-01-05 | B71: Structuring & Smurfing | C71: STR-01 | D71: Multiple transactions just below threshold | E71: Edge | F71: Deposits through different channels (agent, bank transfer, card) | G71: Aggregated across channels; alert raised | H71: High | I71: P1 | J71: Pass | K71: Deposits via agent, bank transfer and card aggregated across channels → 1 alert. | L71: Claude (automated test suite) | M71: 2026-10-15 | O71: Automated: StructuringTests.STR_01_below_threshold
A72: TM-STR-02-01 | B72: Structuring & Smurfing | C72: STR-02 | D72: Split cash-in across multiple agents same day | E72: Positive | F72: C8 cash-in 1,000 at agent A, 1,000 at B, 1,100 at C same day | G72: Alert raised | H72: High | I72: P1 | J72: Pass | K72: 1,000 / 1,000 / 1,100 cash-in at 3 agents same day → 1 alert. | L72: Claude (automated test suite) | M72: 2026-10-15 | O72: Automated: StructuringTests.STR_02_split_cash_in_agents
... A78: TM-STR-03-03 | B78: Structuring & Smurfing | C78: STR-03 | D78: Smurfing — many depositors to one account | E78: Negative | F78: 12 senders, but C9 is a registered merchant | G78: Excluded or uses merchant thresholds | H78: High | I78: P1 | J78: Pass | K78: Receiver is a registered merchant (rule scoped to individuals) → 0 alerts. | L78: Claude (automated test suite) | M78: 2026-10-15 | O78: Automated: StructuringTests.STR_03_smurfing
A79: TM-STR-03-04 | B79: Structuring & Smurfing | C79: STR-03 | D79: Smurfing — many depositors to one account | E79: Edge | F79: 3 of the senders share same device/ID token | G79: Linked parties flagged in evidence | H79: High | I79: P1 | J79: Pass | K79: Alert raised (1); 3 senders share one ID token and are linked by entity resolution, alert evidence flags the linked parties (linkedParties: link type and confidence). | L79: Claude (automated test suite) | M79: 2026-10-15 | N79: DEF-TM-03 (fixed) | O79: Automated: StructuringTests.STR_03_smurfing. Failed in the first execution (DEF-TM-03: Entity-resolution links not usable by rules or shown in evidence); fixed: Subject 'Entity' (linked customers, minimum confidence) and linkedParties in alert evidence; re-tested 2026-10-15.
A80: TM-STR-04-01 | B80: Structuring & Smurfing | C80: STR-04 | D80: Splitting across own multiple wallets | E80: Positive | F80: Person P has 3 wallets each receiving 2,000 same day | G80: Alert at person level | H80: High | I80: P1 | J80: Pass | K80: Same person, 3 wallets each receiving 2,000 → aggregated by resolved customer → 1 person-level alert. | L80: Claude (automated test suite) | M80: 2026-10-15 | O80: Automated: StructuringTests.STR_04_multiple_own_wallets
A81: TM-STR-04-02 | B81: Structuring & Smurfing | C81: STR-04 | D81: Splitting across own multiple wallets | E81: Negative | F81: Single wallet receives 2,000 | G81: No alert | H81: High | I81: P1 | J81: Pass | K81: Single wallet receives 2,000 → 0 alerts. | L81: Claude (automated test suite) | M81: 2026-10-15 | O81: Automated: StructuringTests.STR_04_multiple_own_wallets
A82: TM-STR-04-03 | B82: Structuring & Smurfing | C82: STR-04 | D82: Splitting across own multiple wallets | E82: Edge | F82: Wallets linked only by device, not ID | G82: Alert with entity-resolution confidence shown | H82: High | I82: P1 | J82: Pass | K82: Three customer records linked by a shared device (entity link, confidence 0.6000) each receiving 2,000 → entity-level rule (subject Entity, minimum confidence 0.6) aggregates 6,000 → 1 alert; members, link type and confidence in evidence: True. | L82: Claude (automated test suite) | M82: 2026-10-15 | N82: DEF-TM-03 (fixed) | O82: Automated: StructuringTests.STR_04_multiple_own_wallets. Failed in the first execution (DEF-TM-03: Entity-resolution links not usable by rules or shown in evidence); fixed: Subject 'Entity' (linked customers, minimum confidence) and linkedParties in alert evidence; re-tested 2026-10-15.
A83: TM-STR-05-01 | B83: Structuring & Smurfing | C83: STR-05 | D83: Repeated amount just below wallet limit | E83: Positive | F83: Limit 1,000; transfers of 990, 995, 999 in 5 days | G83: Alert raised | H83: Medium | I83: P1 | J83: Pass | K83: Limit 1,000 (98–100% band configured in the rule); 990/995/999 within 5 days → 1 alert. | L83: Claude (automated test suite) | M83: 2026-10-15 | O83: Automated: StructuringTests.STR_05_just_below_own_limit. Note: a per-customer limit attribute cannot be referenced; the band is a rule parameter.
A84: TM-STR-05-02 | B84: Structuring & Smurfing | C84: STR-05 | D84: Repeated amount just below wallet limit | E84: Negative | F84: Transfers of 500 | G84: No alert | H84: Medium | I84: P1 | J84: Pass | K84: Transfers of 500 → 0 alerts. | L84: Claude (automated test suite) | M84: 2026-10-15 | O84: Automated: StructuringTests.STR_05_just_below_own_limit
A85: TM-STR-05-03 | B85: Structuring & Smurfing | C85: STR-05 | D85: Repeated amount just below wallet limit | E85: Boundary | F85: Two transfers at 999 | G85: No alert | H85: Medium | I85: P1 | J85: Pass | K85: Two transfers at 999 → 0 alerts. | L85: Claude (automated test suite) | M85: 2026-10-15 | O85: Automated: StructuringTests.STR_05_just_below_own_limit
A86: TM-STR-06-01 | B86: Structuring & Smurfing | C86: STR-06 | D86: Structuring across consecutive days | E86: Positive | F86: Daily totals of 4,600, 4,800, 4,700, 4,950 (limit 5,000) on 4 consecutive days | G86: Alert raised | H86: Medium | I86: P2 | J86: Pass | K86: Daily totals 4,600, 4,800, 4,700, 4,950 (limit 5,000, band 90–100%) on 4 consecutive days → 1 alert; daily totals in evidence. | L86: Claude (automated test suite) | M86: 2026-10-15 | O86: Automated: ExtendedCapabilityTests.STR_06_consecutive_days_below_limit. Blocked in the first execution (capability gap); executable after the rule DSL extension.
A87: TM-STR-06-02 | B87: Structuring & Smurfing | C87: STR-06 | D87: Structuring across consecutive days | E87: Negative | F87: Same totals on non-consecutive days | G87: No alert | H87: Medium | I87: P2 | J87: Pass | K87: Same totals on alternate days → 0 alerts. | L87: Claude (automated test suite) | M87: 2026-10-15 | O87: Automated: ExtendedCapabilityTests.STR_06_consecutive_days_below_limit. Blocked in the first execution (capability gap); executable after the rule DSL extension.
A88: TM-STR-06-03 | B88: Structuring & Smurfing | C88: STR-06 | D88: Structuring across consecutive days | E88: Boundary | F88: 3 consecutive days | G88: No alert | H88: Medium | I88: P2 | J88: Pass | K88: 3 consecutive days → 0 alerts. | L88: Claude (automated test suite) | M88: 2026-10-15 | O88: Automated: ExtendedCapabilityTests.STR_06_consecutive_days_below_limit. Blocked in the first execution (capability gap); executable after the rule DSL extension.
A89: TM-RMV-01-01 | B89: Rapid Movement & Pass-through | C89: RMV-01 | D89: Rapid in-and-out (pass-through) | E89: Positive | F89: C10 receives 2,000 at 10:00 and sends 1,900 at 10:25 | G89: Alert raised; in/out pair in evidence | H89: High | I89: P1 | J89: Pass | K89: Received 2,000 at 10:00, sent 1,900 at 10:25 → 1 alert; in/out pair linked in evidence. | L89: Claude (automated test suite) | M89: 2026-10-15 | O89: Automated: RapidMovementFanTests.RMV_01_pass_through
A90: TM-RMV-01-02 | B90: Rapid Movement & Pass-through | C90: RMV-01 | D90: Rapid in-and-out (pass-through) | E90: Boundary | F90: Outgoing at 61 minutes | G90: No alert | H90: High | I90: P1 | J90: Pass | K90: Outgoing at 61 minutes → 0 alerts. | L90: Claude (automated test suite) | M90: 2026-10-15 | O90: Automated: RapidMovementFanTests.RMV_01_pass_through
A91: TM-RMV-01-03 | B91: Rapid Movement & Pass-through | C91: RMV-01 | D91: Rapid in-and-out (pass-through) | E91: Boundary | F91: Outgoing 89% of incoming | G91: No alert | H91: High | I91: P1 | J91: Pass | K91: Outgoing 89% of incoming → 0 alerts. | L91: Claude (automated test suite) | M91: 2026-10-15 | O91: Automated: RapidMovementFanTests.RMV_01_pass_through
A92: TM-RMV-01-04 | B92: Rapid Movement & Pass-through | C92: RMV-01 | D92: Rapid in-and-out (pass-through) | E92: Negative | F92: Receives 300, sends 290 | G92: Below minimum amount; no alert | H92: High | I92: P1 | J92: Pass | K92: Received 300 (< minimum 500), sent 290 → 0 alerts. | L92: Claude (automated test suite) | M92: 2026-10-15 | O92: Automated: RapidMovementFanTests.RMV_01_pass_through
A93: TM-RMV-01-05 | B93: Rapid Movement & Pass-through | C93: RMV-01 | D93: Rapid in-and-out (pass-through) | E93: Edge | F93: Out split into 4 transfers totalling 95% | G93: Aggregated; alert raised | H93: High | I93: P1 | J93: Pass | K93: Outflow split into 4 transfers totalling 95% within 60 min → aggregated → 1 alert. | L93: Claude (automated test suite) | M93: 2026-10-15 | O93: Automated: RapidMovementFanTests.RMV_01_pass_through
A94: TM-RMV-02-01 | B94: Rapid Movement & Pass-through | C94: RMV-02 | D94: Balance kept near zero | E94: Positive | F94: Monthly in/out 6,000 with end-of-day balance always < 5 | G94: Alert raised | H94: Medium | I94: P1 | J94: Blocked | K94: Capability gap — Wallet balances / end-of-day balances are not ingested or available to rules. Closest rule definition rejected by the rule validator: $.condition.conditions[0].field: Unknown field 'wallet.endOfDayBalance': not present in the data-source registry.. | L94: Claude (automated test suite) | M94: 2026-10-15 | N94: GAP-RMV-02 | O94: Automated: CapabilityGapTests.Scenario_not_configurable (rule validator evidence)
A95: TM-RMV-02-02 | B95: Rapid Movement & Pass-through | C95: RMV-02 | D95: Balance kept near zero | E95: Negative | F95: Throughput 1,000 | G95: No alert | H95: Medium | I95: P1 | J95: Blocked | K95: Capability gap — Wallet balances / end-of-day balances are not ingested or available to rules. Closest rule definition rejected by the rule validator: $.condition.conditions[0].field: Unknown field 'wallet.endOfDayBalance': not present in the data-source registry.. | L95: Claude (automated test suite) | M95: 2026-10-15 | N95: GAP-RMV-02 | O95: Automated: CapabilityGapTests.Scenario_not_configurable (rule validator evidence)
A96: TM-RMV-02-03 | B96: Rapid Movement & Pass-through | C96: RMV-02 | D96: Balance kept near zero | E96: Edge | F96: Balance data unavailable from core | G96: Rule marked not evaluated; data-quality item | H96: Medium | I96: P1 | J96: Blocked | K96: Capability gap — Wallet balances / end-of-day balances are not ingested or available to rules. Closest rule definition rejected by the rule validator: $.condition.conditions[0].field: Unknown field 'wallet.endOfDayBalance': not present in the data-source registry.. | L96: Claude (automated test suite) | M96: 2026-10-15 | N96: GAP-RMV-02 | O96: Automated: CapabilityGapTests.Scenario_not_configurable (rule validator evidence)
A97: TM-RMV-03-01 | B97: Rapid Movement & Pass-through | C97: RMV-03 | D97: Incoming then immediate cash-out | E97: Positive | F97: Receives 1,500 transfer, withdraws 1,400 at agent 40 minutes later | G97: Alert raised | H97: High | I97: P1 | J97: Pass | K97: Received 1,500 transfer, cashed out 1,400 at agent 40 min later → 1 alert. | L97: Claude (automated test suite) | M97: 2026-10-15 | O97: Automated: RapidMovementFanTests.RMV_03_incoming_then_cash_out. Note: the outgoing leg cannot be restricted to cash-out type in the DSL (any outflow counts).
A98: TM-RMV-03-02 | B98: Rapid Movement & Pass-through | C98: RMV-03 | D98: Incoming then immediate cash-out | E98: Negative | F98: Withdraws after 3 days | G98: No alert | H98: High | I98: P1 | J98: Pass | K98: Withdrawal after 3 days → 0 alerts. | L98: Claude (automated test suite) | M98: 2026-10-15 | O98: Automated: RapidMovementFanTests.RMV_03_incoming_then_cash_out
A99: TM-RMV-03-03 | B99: Rapid Movement & Pass-through | C99: RMV-03 | D99: Incoming then immediate cash-out | E99: Edge | F99: Cash-out at ATM abroad | G99: Alert plus geographic flag | H99: High | I99: P1 | J99: Pass | K99: Cash-out at ATM abroad → 1 alert carrying the indicator flag 'Geographic: cash-out abroad' (rule action.indicators); the domestic case has no flag: True. | L99: Claude (automated test suite) | M99: 2026-10-15 | N99: DEF-TM-04 (fixed) | O99: Automated: RapidMovementFanTests.RMV_03_incoming_then_cash_out. Failed in the first execution (DEF-TM-04: No secondary indicator flags / severity escalation); fixed: action.indicators (flag + optional severity) and counterparty.* fields; re-tested 2026-10-15.
A100: TM-RMV-04-01 | B100: Rapid Movement & Pass-through | C100: RMV-04 | D100: Layering chain (multi-hop) | E100: Positive | F100: A→B 1,000; B→C 950; C→D 920 within 6 hours | G100: Alert on chain with all hops in evidence | H100: High | I100: P2 | J100: Blocked | K100: Capability gap — cycle detects funds returning to the subject only; no open multi-hop chain (A→B→C→D) with per-hop retention. Closest rule definition rejected by the rule validator: $.condition.aggregate: Unknown aggregate 'chain'. Allowed: count, sum, distinctCounterparties, ratio, rapidMovement, dormancyDays, profileRatio, peerRatio, newCustomers, customersPerDevice, cycle, newCountries, historyCount, historySum, historyRatio, distinctCount, reciprocalCount, consecutiveDays, newCounterpartyShare, sharedDeviceSenders, typeShareChange, minutesSinceEvent.. | L100: Claude (automated test suite) | M100: 2026-10-15 | N100: GAP-RMV-04 | O100: Automated: CapabilityGapTests.Scenario_not_configurable (rule validator evidence)
A101: TM-RMV-04-02 | B101: Rapid Movement & Pass-through | C101: RMV-04 | D101: Layering chain (multi-hop) | E101: Negative | F101: Hops separated by 3 days | G101: No alert | H101: High | I101: P2 | J101: Blocked | K101: Capability gap — cycle detects funds returning to the subject only; no open multi-hop chain (A→B→C→D) with per-hop retention. Closest rule definition rejected by the rule validator: $.condition.aggregate: Unknown aggregate 'chain'. Allowed: count, sum, distinctCounterparties, ratio, rapidMovement, dormancyDays, profileRatio, peerRatio, newCustomers, customersPerDevice, cycle, newCountries, historyCount, historySum, historyRatio, distinctCount, reciprocalCount, consecutiveDays, newCounterpartyShare, sharedDeviceSenders, typeShareChange, minutesSinceEvent.. | L101: Claude (automated test suite) | M101: 2026-10-15 | N101: GAP-RMV-04 | O101: Automated: CapabilityGapTests.Scenario_not_configurable (rule validator evidence)
A102: TM-RMV-04-03 | B102: Rapid Movement & Pass-through | C102: RMV-04 | D102: Layering chain (multi-hop) | E102: Boundary | F102: Only 2 hops | G102: No alert | H102: High | I102: P2 | J102: Blocked | K102: Capability gap — cycle detects funds returning to the subject only; no open multi-hop chain (A→B→C→D) with per-hop retention. Closest rule definition rejected by the rule validator: $.condition.aggregate: Unknown aggregate 'chain'. Allowed: count, sum, distinctCounterparties, ratio, rapidMovement, dormancyDays, profileRatio, peerRatio, newCustomers, customersPerDevice, cycle, newCountries, historyCount, historySum, historyRatio, distinctCount, reciprocalCount, consecutiveDays, newCounterpartyShare, sharedDeviceSenders, typeShareChange, minutesSinceEvent.. | L102: Claude (automated test suite) | M102: 2026-10-15 | N102: GAP-RMV-04 | O102: Automated: CapabilityGapTests.Scenario_not_configurable (rule validator evidence)
A103: TM-RMV-04-04 | B103: Rapid Movement & Pass-through | C103: RMV-04 | D103: Layering chain (multi-hop) | E103: Edge | F103: One hop through internal clearing wallet | G103: Clearing wallet skipped; chain still detected | H103: High | I103: P2 | J103: Blocked | K103: Capability gap — cycle detects funds returning to the subject only; no open multi-hop chain (A→B→C→D) with per-hop retention. Closest rule definition rejected by the rule validator: $.condition.aggregate: Unknown aggregate 'chain'. Allowed: count, sum, distinctCounterparties, ratio, rapidMovement, dormancyDays, profileRatio, peerRatio, newCustomers, customersPerDevice, cycle, newCountries, historyCount, historySum, historyRatio, distinctCount, reciprocalCount, consecutiveDays, newCounterpartyShare, sharedDeviceSenders, typeShareChange, minutesSinceEvent.. | L103: Claude (automated test suite) | M103: 2026-10-15 | N103: GAP-RMV-04 | O103: Automated: CapabilityGapTests.Scenario_not_configurable (rule validator evidence)
A104: TM-RMV-05-01 | B104: Rapid Movement & Pass-through | C104: RMV-05 | D104: Loan/credit disbursement moved out immediately | E104: Positive | F104: Nano-loan 500 disbursed, 480 sent to third party in 2 hours | G104: Alert raised | H104: Medium | I104: P3 | J104: Pass | K104: Nano-loan 500 disbursed, 480 sent to third party after 2 h (96%) → 1 alert. | L104: Claude (automated test suite) | M104: 2026-10-15 | O104: Automated: RapidMovementFanTests.RMV_05_loan_disbursement_moved_out
A105: TM-RMV-05-02 | B105: Rapid Movement & Pass-through | C105: RMV-05 | D105: Loan/credit disbursement moved out immediately | E105: Negative | F105: Disbursement spent gradually at merchants | G105: No alert | H105: Medium | I105: P3 | J105: Pass | K105: Disbursement spent gradually at merchants over 10 days → 0 alerts. | L105: Claude (automated test suite) | M105: 2026-10-15 | O105: Automated: RapidMovementFanTests.RMV_05_loan_disbursement_moved_out
A106: TM-FAN-01-01 | B106: Fan-in / Fan-out | C106: FAN-01 | D106: Many senders to one receiver (fan-in) | E106: Positive | F106: 22 distinct senders send to C11 within 5 days | G106: Alert raised | H106: High | I106: P1 | J106: Pass | K106: 22 distinct senders within 5 days → 1 alert. | L106: Claude (automated test suite) | M106: 2026-10-15 | O106: Automated: RapidMovementFanTests.FAN_01_fan_in
A107: TM-FAN-01-02 | B107: Fan-in / Fan-out | C107: FAN-01 | D107: Many senders to one receiver (fan-in) | E107: Boundary | F107: 19 senders | G107: No alert | H107: High | I107: P1 | J107: Pass | K107: 19 senders → 0 alerts. | L107: Claude (automated test suite) | M107: 2026-10-15 | O107: Automated: RapidMovementFanTests.FAN_01_fan_in
...

Sheet Legend
A1: How to use | B1: Each scenario in 'Scenario Catalogue' is a configurable detection rule. 'Test Cases' prove it fires when it should (Positive), stays silent when it should (Negative), behaves correctly at the threshold (Boundary) and handles awkward data (Edge). Fill the shaded columns; Summary updates automatically.
A2: Example row | B2: TM-VEL-01-01 → Status: Pass · Actual Result: Alert ALR-000123 raised on 20th withdrawal, evidence lists 20 txns · Tester: QA1 · Execution Date: 2026-10-20
A3: Test types | B3: Positive = must alert. Negative = must not alert. Boundary = exactly at / just past the threshold. Edge = data or timing conditions (reversals, missing data, multiple wallets, time zones, VPN, late arrival).
A4: Parameters | B4: All thresholds (N, A, T, D, P...) are example defaults to make the tests concrete. Replace with values approved by compliance; boundary tests must be updated when a threshold changes.
A5: Amounts and time | B5: Amounts in JOD unless stated; other currencies are converted with the versioned FX rate. Calendar windows use local time (Asia/Amman); 'rolling' windows ignore calendar days.
A6: Counting rules | B6: Unless a test says otherwise: only Completed transactions count; aggregation is by resolved customer across all their wallets; fees and internal clearing legs are excluded; reversals follow each rule's netting policy.
A7: Expected result | B7: 'Alert raised' means one alert with severity as listed, the rule version, window boundaries and the matched transactions stored as evidence. Real-time scenarios (sanctions, sanctioned countries) also expect a Hold/Reject decision.
A8: Typology basis | B8: Scenarios follow red-flag typologies published by the FATF (e.g. guidance on money or value transfer services, prepaid cards/mobile/internet payments, terrorist financing and crowdfunding, virtual-asset red flags) and the Wolfsberg Group, adapted to an e-wallet/agent model.
A9: Test data | B9: Use fictitious customers (C1, C2...), wallets and test list entries only. Never use real customer data or real sanctions-list persons outside controlled test lists.
A10: Category codes | B10: VEL = Velocity & Frequency · AMT = Amount & Thresholds · STR = Structuring & Smurfing · RMV = Rapid Movement & Pass-through · FAN = Fan-in / Fan-out · GEO = Geographic & Impossible Travel · DEV = Device, IP & Channel · BEH = Behavioural Change & Profile Mismatch · CSH = Cash-in / Cash-out · AGT = Agent Network · MER = Merchant · REV = Reversals, Refunds & Failed Attempts · CIR = Circular & Related-party · MUL = Money Mule · XBR = Cross-border Remittance · PRP = Top-ups, Vouchers & Bill Payments · TF = Terrorist Financing Indicators · SAN = Sanctions & High-risk Counterparties · ATO = Account Takeover Overlap (FRAML) · VAG = Virtual Assets & Gambling · ENG = Engine Edge Cases (applies to all scenarios)

Sheet Defects & Gaps
A1: ID | B1: Type | C1: Description | D1: Affected test cases
A2: DEF-TM-01 | B2: Fixed and re-tested | C2: Own-wallet / self-transfer exclusion not configurable. Fix: Rule field txn.isOwnAccount | D2: TM-VEL-03-03
A3: DEF-TM-02 | B3: Fixed and re-tested | C3: Missing profile/attribute data silently evaluated as no-match. Fix: Missing inputs raise RuleInputMissing data-quality items (result incomplete) | D3: TM-AMT-03-04, TM-BEH-04-03
A4: DEF-TM-03 | B4: Fixed and re-tested | C4: Entity-resolution links not usable by rules or shown in evidence. Fix: Subject 'Entity' (linked customers, minimum confidence) and linkedParties in alert evidence | D4: TM-STR-03-04, TM-STR-04-03
A5: DEF-TM-04 | B5: Fixed and re-tested | C5: No secondary indicator flags / severity escalation. Fix: action.indicators (flag + optional severity) and counterparty.* fields | D5: TM-RMV-03-03, TM-FAN-01-04, TM-FAN-02-04
A6: DEF-TM-05 | B6: Fixed and re-tested | C6: Runs used the active rule version for all transactions. Fix: Manual runs evaluate each period with the version in force at transaction time | D6: TM-GEO-03-03
A7: DEF-TM-06 | B7: Fixed and re-tested | C7: No per-customer behavioural baseline. Fix: historyCount / historySum / historyRatio aggregates over the customer's own lookback | D7: TM-BEH-03-02
A8: DEF-TM-07 | B8: Fixed and re-tested | C8: Real-time list hits created no AML alert. Fix: Real-time list matches raise Critical/High alerts | D8: TM-SAN-01-01, TM-SAN-04-01
A9: DEF-TM-08 | B9: Fixed and re-tested | C9: Keyword matching without normalisation. Fix: contains normalises case, diacritics and letter spacing | D9: TM-SAN-02-03
A10: DEF-TM-09 | B10: Fixed and re-tested | C10: Later reversal not noted on the alert. Fix: LinkedTransactionReversed entry in alert history | D10: TM-ENG-02-03
A11: DEF-TM-10 | B11: Fixed and re-tested | C11: Late arrivals never re-evaluated / not logged. Fix: Scheduler re-evaluates late arrivals within Rules:LateArrivalLookbackDays; older ones raise LateArrivalNotEvaluated | D11: TM-ENG-06-01, TM-ENG-06-02
A12: DEF-TM-11 | B12: Fixed and re-tested | C12: No wallet-level aggregation; unresolved parties not evaluated. Fix: Subject 'Wallet' and unresolvedParties = Wallet | D12: TM-ENG-07-01, TM-ENG-07-02
... A41: GAP-XBR-03 | B41: Capability gap (test cases Blocked) | C41: Capability gap — No corridor share per peer group (nationality/segment). Closest rule definition rejected by the rule validator: $.condition.aggregate: Unknown aggregate 'corridorPeerShare'. Allowed: count, sum, distinctCounterparties, ratio, rapidMovement, dormancyDays, profileRatio, peerRatio, newCustomers, customersPerDevice, cycle, newCountries, historyCount, historySum, historyRatio, distinctCount, reciprocalCount, consecutiveDays, newCounterpartyShare, sharedDeviceSenders, typeShareChange, minutesSinceEvent.. | D41: TM-XBR-03-01, TM-XBR-03-02
